trunk/misc/articulos/impvl/src/funcion/funcion.v
//-----------------------------------------------------------------------------
// Title         : Funcion
// Project       : Laboratorios de Digitales I
//-----------------------------------------------------------------------------
// File          : function.v
// Author        : Mauricio Velasquez Velasquez  <mvelasquez@glud.udistrital.edu.co>
// Created       : 26.10.2004
// Last modified : 26.10.2004
//-----------------------------------------------------------------------------
// Description :
// ImplementaciOn de una funciOn de lOgica combinacional.
//-----------------------------------------------------------------------------
// Copyright (c) 2004 by GLUD-electronica (Electronix) This model is the confidential and
// proprietary property of GLUD-electronica (Electronix) and the possession or use of this
// file requires a written license from GLUD-electronica (Electronix).
//------------------------------------------------------------------------------
// Modification history :
// 26.10.2004 : created
//-----------------------------------------------------------------------------

module funcion (a, b, c, z);

      input a, b, c;
      output z;
      reg  z;

      always @ (a or b or c) begin

	 z = (!a && b) || (b && !c) || (a && !c);
	 
      end
   
endmodule // funcion


module funcion_tb;

   reg a, b, c;
   wire z;

   initial begin
      a = 0;
      b = 0;
      c = 0;
      
   end
   always begin
      #1 a=~a;
   end
   
   always begin
      #2 b=~b;
   end
   
   always begin
      #4 c=~c;
   end
   
   initial begin
     #9 $finish;
      
   end
   
   funcion Ufuncion_tb(a, b, c, z);
   

   initial begin
      $dumpfile ("funcion.vcd");
      $dumpvars;

   end   
   
endmodule // funcion_tb

trunk/misc/articulos/impvl/src/funcion/funcion.vcd
$date
	Tue Oct 26 04:36:07 2004
$end
$version
	Icarus Verilog
$end
$timescale
	1s
$end
$scope module funcion_tb $end
$var wire 1 ! z $end
$var reg 1 " a $end
$var reg 1 # b $end
$var reg 1 $ c $end
$scope module Ufuncion_tb $end
$var wire 1 " a $end
$var wire 1 # b $end
$var wire 1 $ c $end
$var reg 1 ! z $end
$upscope $end
$upscope $end
$enddefinitions $end
#0
$dumpvars
0$
0#
0"
0!
$end
#1
1!
1"
#2
0"
1#
#3
1"
#4
0!
0"
0#
1$
#5
1"
#6
1!
0"
1#
#7
0!
1"
#8
0"
0#
0$
