trunk/talleres/CampusPartyColombia2009/SumadorCompleto.v
module SumadorCompleto (Bit1, Bit2, CarryIn, Sum, CarryOut); //Descripcion de bloque FullAdder con 5 conexiones
   //este bloque permite sumar 2 bit con acarreo de entrada y salida para uso en cascada
	input Bit1, Bit2, CarryIn; //Bit1 y Bit2 son los sumandos, CarryIn el acarreo de entrada
	output Sum, CarryOut;      //Sum es la suma de los bits y CarryOut el acarreo de salida

	wire   W1, W2, W3;         //"Cables" que se usan para conexiones entre compuertas

	assign W1 = Bit1 & Bit2;    //Compuerta A1, entradas: Bit1 y Bit2, salida: W1
	assign W2 = Bit1 ^ Bit2;    //Compuerta X1, entradas: Bit1 y Bit2, salida: W2
	assign W3 = W2 & CarryIn;   //Compuerta A2, entradas: W2 y CarryIn, salida: W3
	assign CarryOut = W1 | W3;  //Compuerta O1, entradas: W1 y W3, salida: CarryOut
	assign Sum = CarryIn ^ W2;  //Compuerta X2, entradas: CarryIn y W2, salida: Sum
	
endmodule // Fin de la descripción del bloque SumadorCompleto

/*NOTA:
 Notacion didactica para compuertas:
 A1 = Primera compuerta AND
 A2 = Segunda compuerta AND
 O1 = Primera compuerta OR
 X1 = Primera compuerta XOR
 X2 = Segunda compuerta XOR

 La notación estandar para esquematicos usa la letra U, ej: U1,U2 ...*/

/*TODO:
 Averiguar cual es el estandar para esquemáticos que dice que se usa la U, en http://en.wikipedia.org/wiki/Circuit_diagram se habla de la ANSI y de la IEC y esta referencia puede ser una pista: http://std.iec.ch/iec60617*/

trunk/talleres/CampusPartyColombia2009/SumadorCompleto_Lab.v
module Laboratorio;
   reg  [2:0] Entrada;
   wire [1:0] Salida;

   SumadorCompleto InstanciaSumCompleto(Entrada[1], Entrada[2], Entrada[0], Salida[1], Salida[0]);

   initial begin
      Entrada = 'b000;
   end

   initial begin
      repeat (8) begin
	 #1 Entrada <= Entrada+1;
      end
      
   end

   initial begin
      $dumpfile ("SumadorCompleto.vcd");
      $dumpvars;
   end

endmodule // Laboratorio

trunk/talleres/CampusPartyColombia2009/SumadorCompleto.vcd
$date
	Wed Jul  1 10:05:12 2009
$end
$version
	Icarus Verilog
$end
$timescale
	1s
$end
$scope module Laboratorio $end
$var wire 2 ! Salida[1:0] $end
$var reg 3 " Entrada[2:0] $end
$scope module InstanciaSumCompleto $end
$var wire 1 # Bit1 $end
$var wire 1 $ Bit2 $end
$var wire 1 % CarryIn $end
$var wire 1 & CarryOut $end
$var wire 1 ' Sum $end
$var wire 1 ( W1 $end
$var wire 1 ) W2 $end
$var wire 1 * W3 $end
$upscope $end
$upscope $end
$enddefinitions $end
#0
$dumpvars
0*
0)
0(
0'
0&
0%
0$
0#
b0 "
b0 !
$end
#1
b10 !
1'
b1 "
1%
#2
1)
b10 !
1'
1#
b10 "
0%
#3
1&
1*
b1 !
0'
b11 "
1%
#4
0&
1)
0*
b10 !
1'
1$
0#
b100 "
0%
#5
1&
1*
b1 !
0'
b101 "
1%
#6
1&
1(
0)
0*
b1 !
0'
1#
b110 "
0%
#7
b11 !
1'
b111 "
1%
#8
0&
0(
0)
b0 !
0'
0$
0#
b0 "
0%
