ld2ud/code/ciscud/ciscud/Cero.v
module Cero (/*AUTOARG*/
   // Outputs
   Salida
   ) ;
   output [15:0] Salida;

   assign Salida = 16'h0;
endmodule // Cero

ld2ud/code/ciscud/Cero_Lab.v
module Cero_Lab (/*AUTOARG*/ ) ;
   wire   [15:0] Respuesta;

   Cero Cero (Respuesta);


   //Simulación:
   //como no hay nada en la salida hay que crear algo que cambie en el tiempo para que exista siulación
   reg   [2:0] Reloj;
   initial begin
      Reloj = 2'b000;
   end
   initial begin
      repeat (8) begin
	 #1 Reloj <= Reloj+1;
      end
   end
   initial begin
      $dumpfile ("Cero_Lab.vcd");
      $dumpvars;
   end
   
endmodule // Cero_Lab

ld2ud/code/ciscud/Cero_Lab.vcd
$date
	Tue Dec  1 22:38:55 2009
$end
$version
	Icarus Verilog
$end
$timescale
	1s
$end
$scope module Cero_Lab $end
$var wire 16 ! Respuesta[15:0] $end
$var reg 3 " Reloj[2:0] $end
$scope module Cero $end
$var wire 16 # Salida[15:0] $end
$upscope $end
$upscope $end
$enddefinitions $end
#0
$dumpvars
b0 #
b0 "
b0 !
$end
#1
b1 "
#2
b10 "
#3
b11 "
#4
b100 "
#5
b101 "
#6
b110 "
#7
b111 "
#8
b0 "
