ld2ud/code/ciscud/UnidadDeControl.v
module UnidadDeControl (/*AUTOARG*/
   // Outputs
   Control, LoadSelect, WriteAddress, ReadAddressA, ReadAddressB, Fun,
   // Inputs
   Instruccion, Reloj, Reiniciar
   ) ;
   
   output reg [5:0] Control;
/* -----\/----- EXCLUDED -----\/-----
   
   output reg 	    LoadS;
   output reg [1:0] SelectS;
   output reg 	    NegS;
 -----/\----- EXCLUDED -----/\----- */

/* -----\/----- EXCLUDED -----\/-----
   
   //se dejará LoadSelect directamente, no logré
   //partir la tupla en salidas diferentes
   //por que es un reg y la asignación procedular
   //no funcionó como esperaba y no tengo tiempo
   output reg 	    SelectDR, LoadDR;
   output reg 	    SelectAR, LoadAR;
   
   output reg [1:0] SelectPC;
   output reg 	    LoadPC;
   
   output reg 	    LoadIR, LoadCR;
   output reg 	     WriteSelect, WriteEnable;
 -----/\----- EXCLUDED -----/\----- */
   //La siguiente linea reemplaza el codigo comentareado arriba
   output reg [10:0] LoadSelect;
   
   output reg [2:0]  WriteAddress, ReadAddressA, ReadAddressB;
   
   output reg [3:0]  Fun;
   


   input  [15:0] Instruccion;
//   input  StatusFlag;
   input  Reloj, Reiniciar;
   

   localparam [6:0]
     SF1   = 6'b000000,
     SF2   = 6'b000001,
     SF3   = 6'b000010,
     
     S01   = 6'b000011,
     S02   = 6'b000100,
     S031  = 6'b000101,
     S032  = 6'b000110,
     S04   = 6'b000111,
     
     S1R01 = 6'b001000,
     S1R11 = 6'b001001,
     S1R12 = 6'b001010,
     S1W10 = 6'b001011,
     S1W11 = 6'b001100,
     S1R21 = 6'b001101,
     S1R22 = 6'b001110,
     S1R23 = 6'b001111,
     S1W20 = 6'b010000,
     S1W21 = 6'b010001,
     S1W22 = 6'b010010,
     S1R31 = 6'b010011,
     S1R32 = 6'b010100,
     S1R33 = 6'b010101,
     S1W30 = 6'b010110,
     S1W31 = 6'b010111,
     S1W32 = 6'b011000,
     
     S21   = 6'b011001,
     S22   = 6'b011010,
     S23   = 6'b011011,
     S24   = 6'b011100,
     S25   = 6'b011101,
     S26   = 6'b011110,
     S27   = 6'b011111,
     S28   = 6'b100000;
/* -----\/----- EXCLUDED -----\/-----

//arriba esto quedo directo como salida por que no funciono el "desensamble" de LoadSelect
 // en varias tuplas
   reg [10:0] LoadSelect;  //habilitadores en una palabra (excepto los de Satus)
                              //(referencia en hoja de calculo UnidadDeControl_Operaciones.ods)
   always @* begin
      LoadSelect <= {SelectDR,LoadDR,
			SelectAR,LoadAR,
			SelectPC,LoadPC,
			LoadIR,LoadCR,
			WriteSelect,WriteEnable};
   end
 -----/\----- EXCLUDED -----/\----- */

   
/* -----\/----- EXCLUDED -----\/-----
   
   reg [3:0]  ControlStatus;
   always @* begin
      ControlStatus <= {LoadS,SelectS,NegS};
   end
 -----/\----- EXCLUDED -----/\----- */
   
   
   reg   [6:0] EstadoPresente, EstadoFuturo;

   always @ (posedge Reloj, posedge Reiniciar) //Registro de estado
     if (Reiniciar) begin // es el mismo reset del camino de datos que reinicializa
	                  // todos los registros y garantiza CR <= (--) && PC<=0
	EstadoFuturo <= SF1;
     end 
     else
       EstadoPresente <= EstadoFuturo;

      
   always @* //EntradaCombinacional
     case (EstadoPresente)
       SF1: begin
	  EstadoFuturo <= SF2;
	  Control      <= 6'b100_100;
	  LoadSe lect   <= 11'bzzzz_zzz_z1zz;
	  WriteAddress <= 3'bzzz;
	  ReadAddressA <= 3'bzzz;
	  ReadAddressB <= 3'bzzz;
	  Fun          <= 4'bzzzz;
       end
       SF2: begin
	  EstadoFuturo <= SF3;
	  Control      <= 6'bzzz_zzz;
	  LoadSelect   <= 11'bzzzz_111_1zzz;
	  WriteAddress <= 3'bzzz;
	  ReadAddressA <= 3'bzzz;
	  ReadAddressB <= 3'bzzz;
	  Fun          <= 4'bzzzz;
       end
       SF3: begin
	  if (Instruccion[15])  begin
	     if (Instruccion[14]) begin
		EstadoFuturo <= SF1;
	     end
	     else begin
		if (Instruccion[13]) begin
		   if (Instruccion[12]) begin
		      EstadoFuturo <= S27;
		   end
		   else begin
		      EstadoFuturo <= S23;
		   end
		end
		else begin
		   if (Instruccion[12]) begin
//pendiente, es aqui cuando se revisa status		      
		   end
		   else begin
		      EstadoFuturo <= S21;
		   end
		end
	     end
	  end
	  else begin
	     if (Instruccion[14]) begin
		if (Instruccion[10]) begin
		   if (Instruccion[9]) begin
		      if (Instruccion[11]) begin
			 EstadoFuturo <= S1W30;
		      end
		      else begin
			 EstadoFuturo <= S1R31;
		      end
		   end
		   else begin
		      if (Instruccion[11]) begin
			 EstadoFuturo <= S1W20;
		      end
		      else begin
			 EstadoFuturo <= S1R21;
		      end
		   end
		end
		else begin
		   if (Instruccion[9]) begin
		      if (Instruccion[11]) begin
			 EstadoFuturo <= S1W10;
		      end
		      else begin
			 EstadoFuturo <= S1R11;
		      end
		   end
		   else begin
		      EstadoFuturo <= S1R01;
		   end
		end
	     end
	     else begin
		if (Instruccion[12]) begin
		   if (Instruccion[11]) begin
		      EstadoFuturo <= S04;
		   end
		   else begin
		      //estado desconocido pendiente
		   end
		end
		else begin
		   if (Instruccion[11]) begin
		      EstadoFuturo <= S02;
		   end
		   else begin
		      EstadoFuturo <= S01;
		   end
		end
	     end
	  end
       end
       S01: begin
	  EstadoFuturo <= SF1;
	  Control      <= 6'bzzz_zzz;
	  LoadSelect   <= 11'bzzzz_zzz_zz01;
	  WriteAddress <= Instruccion[8:6];
	  ReadAddressA <= Instruccion[5:3];
	  ReadAddressB <= Instruccion[2:0];
	  Fun          <= Instruccion[12:9];
       end
       S02: begin
	  EstadoFuturo <= SF1;
	  Control      <= 6'bzzz_zzz;
	  LoadSelect   <= 11'bzzzz_zzz_zz01;
	  WriteAddress <= Instruccion[8:6];
	  ReadAddressA <= Instruccion[5:3];
	  ReadAddressB <= Instruccion[2:0];
	  Fun          <= Instruccion[12:9];
       end
/* -----\/----- EXCLUDED -----\/-----
       S031: begin
	  EstadoFuturo <= SF1;
	  Control      <= 6'bzzz_zzz;
	  LoadSelect   <= 11'b;
	  WriteAddress <= 3'bzzz;
	  ReadAddressA <= 3'bzzz;
	  ReadAddressB <= 3'bzzz;
	  Fun          <= 4'bzzzz;
       end
       S032: begin
	  EstadoFuturo <= SF1;
	  Control      <= 6'bzzz_zzz;
	  LoadSelect   <= 11'b;
	  WriteAddress <= 3'bzzz;
	  ReadAddressA <= 3'bzzz;
	  ReadAddressB <= 3'bzzz;
	  Fun          <= 4'bzzzz;
       end
 -----/\----- EXCLUDED -----/\----- */
       S04: begin
	  EstadoFuturo <= SF1;
	  Control      <= 6'bzzz_zzz;
	  LoadSelect   <= 11'bzzzz_zzz_zz01;
	  WriteAddress <= Instruccion[8:6];
	  ReadAddressA <= Instruccion[5:3];
	  ReadAddressB <= 3'bzzz;
	  Fun          <= Instruccion[12:9];
       end
       S1R01: begin
	  EstadoFuturo <= SF1;
	  Control      <= 6'bzzz_zzz;
	  LoadSelect   <= 11'bzzzz_111_zz11;
	  WriteAddress <= Instruccion[8:6];
	  ReadAddressA <= 3'bzzz;
	  ReadAddressB <= 3'bzzz;
	  Fun          <= 4'bzzzz;
       end
       S1R11: begin
	  EstadoFuturo <= S1R12;
	  Control      <= 6'b100010;
	  LoadSelect   <= 11'bzz01_zzz_z1zz;
	  WriteAddress <= 3'bzzz;
	  ReadAddressA <= 3'bzzz;
	  ReadAddressB <= 3'bzzz;
	  Fun          <= 4'bzzzz;
       end
       S1R12: begin
	  EstadoFuturo <= SF1;
	  Control      <= 6'bzzz_zzz;
	  LoadSelect   <= 11'bzzzz_111_zz11;
	  WriteAddress <= Instruccion[8:6];
	  ReadAddressA <= 3'bzzz;
	  ReadAddressB <= 3'bzzz;
	  Fun          <= 4'bzzzz;
       end
       S1W10: begin
	  EstadoFuturo <= S1W11;
	  Control      <= 6'b001011;
	  LoadSelect   <= 11'b1101_zzz_z1z0;
	  WriteAddress <= 3'bzzz;
	  ReadAddressA <= Instruccion[5:3];
	  ReadAddressB <= 3'bzzz;
	  Fun          <= 4'b1000;
       end
       S1W11: begin
	  EstadoFuturo <= SF1;
	  Control      <= 6'b001010;
	  LoadSelect   <= 11'bzzzz_111_z1zz;
	  WriteAddress <= 3'bzzz;
	  ReadAddressA <= 3'bzzz;
	  ReadAddressB <= 3'bzzz;
	  Fun          <= 4'bzzzz;
       end
       S1R21: begin
	  EstadoFuturo <= S1R22;
	  Control      <= 6'bzzz_zzz;
	  LoadSelect   <= 11'bzzzz_zzz_zz11;
	  WriteAddress <= Instruccion[8:6];
	  ReadAddressA <= 3'bzzz;
	  ReadAddressB <= 3'bzzz;
	  Fun          <= 4'bzzzz;
       end
       S1R22: begin
	  EstadoFuturo <= S1R23;
	  Control      <= 6'b100010;
	  LoadSelect   <= 11'bzz11_zzz_z1zz;
	  WriteAddress <= 3'bzzz;
	  ReadAddressA <= Instruccion[8:6];
	  ReadAddressB <= Instruccion[2:0];
	  Fun          <= 4'b0101;
       end
       S1R23: begin
	  EstadoFuturo <= SF1;
	  Control      <= 6'bzzz_zzz;
	  LoadSelect   <= 11'bzzzz_111_zz11;
	  WriteAddress <= Instruccion[8:6];
	  ReadAddressA <= 3'bzzz;
	  ReadAddressB <= 3'bzzz;
	  Fun          <= 4'bzzzz;
       end
       S1W20: begin
	  EstadoFuturo <= S1W21;
	  Control      <= 6'bzzz_zzz;
	  LoadSelect   <= 11'b11zz_zzz_zz11;
	  WriteAddress <= Instruccion[5:3];
	  ReadAddressA <= Instruccion[5:3];
	  ReadAddressB <= 3'bzzz;
	  Fun          <= 4'b1000;
       end
       S1W21: begin
	  EstadoFuturo <= S1W22;
	  Control      <= 6'b001011;
	  LoadSelect   <= 11'bzz11_zzz_z1zz;
	  WriteAddress <= 3'bzzz;
	  ReadAddressA <= Instruccion[5:3];
	  ReadAddressB <= Instruccion[2:0];
	  Fun          <= 4'b0101;
       end
       S1W22: begin
	  EstadoFuturo <= SF1;
	  Control      <= 6'b001010;
	  LoadSelect   <= 11'bzzzz_111_z111;
	  WriteAddress <= Instruccion[5:3];
	  ReadAddressA <= 3'bzzz;
	  ReadAddressB <= 3'bzzz;
	  Fun          <= 4'bzzzz;
       end
       S1R31: begin
	  EstadoFuturo <= S1R32;
	  Control      <= 6'b100010;
	  LoadSelect   <= 11'bzz01_zzz_z1zz;
	  WriteAddress <= 3'bzzz;
	  ReadAddressA <= 3'bzzz;
	  ReadAddressB <= 3'bzzz;
	  Fun          <= 4'bzzzz;
       end
       S1R32: begin
	  EstadoFuturo <= S1R33;
	  Control      <= 6'bzzz_zzz;
	  LoadSelect   <= 11'bzz01_zzz_zzzz;
	  WriteAddress <= 3'bzzz;
	  ReadAddressA <= 3'bzzz;
	  ReadAddressB <= 3'bzzz;
	  Fun          <= 4'bzzzz;
       end
       S1R33: begin
	  EstadoFuturo <= SF1;
	  Control      <= 6'bzzz_zzz;
	  LoadSelect   <= 11'bzzzz_11_zz11;
	  WriteAddress <= Instruccion[8:6];
	  ReadAddressA <= 3'bzzz;
	  ReadAddressB <= 3'bzzz;
	  Fun          <= 4'bzzzz;
       end
       S1W30: begin
	  EstadoFuturo <= S1W31;
	  Control      <= 6'b100010;
	  LoadSelect   <= 11'bzz01_zzz_z1zz;
	  WriteAddress <= 3'bzzz;
	  ReadAddressA <= 3'bzzz;
	  ReadAddressB <= 3'bzzz;
	  Fun          <= 4'bzzzz;
       end
       S1W31: begin
	  EstadoFuturo <= S1W32;
	  Control      <= 6'b001011;
	  LoadSelect   <= 11'b1101_zzz_z1zz;
	  WriteAddress <= 3'bzzz;
	  ReadAddressA <= Instruccion[5:3];
	  ReadAddressB <= 3'bzzz;
	  Fun          <= 4'b1000;
       end
       S1W32: begin
	  EstadoFuturo <= SF1;
	  Control      <= 6'b001010;
	  LoadSelect   <= 11'bzzzz_111_z1zzz;
	  WriteAddress <= 3'bzzz;
	  ReadAddressA <= 3'bzzz;
	  ReadAddressB <= 3'bzzz;
	  Fun          <= 4'bzzzz;
       end
       S21: begin
	  EstadoFuturo <= SF1;
	  Control      <= 6'bzzz_zzz;
	  LoadSelect   <= 11'bzzzz_001_zzzz;
	  WriteAddress <= 3'bzzz;
	  ReadAddressA <= 3'bzzz;
	  ReadAddressB <= 3'bzzz;
	  Fun          <= 4'bzzzz;
       end
       S22: begin
	  EstadoFuturo <= SF1;
	  Control      <= 6'bzzz_zzz;
	  LoadSelect   <= 11'bzzzz_111_zzzz;
	  WriteAddress <= 3'bzzz;
	  ReadAddressA <= 3'bzzz;
	  ReadAddressB <= 3'bzzz;
	  Fun          <= 4'bzzzz;
       end
       S23: begin
	  EstadoFuturo <= S24;
	  Control      <= 6'b010011;
	  LoadSelect   <= 11'b0111_111_z1zz;
	  WriteAddress <= 3'bzzz;
	  ReadAddressA <= Instruccion[5:3];
	  ReadAddressB <= 3'bzzz;
	  Fun          <= 4'b1000;
       end
       S24: begin
	  EstadoFuturo <= S25;
	  Control      <= 6'b010010;
	  LoadSelect   <= 11'bzzzz_zzz_z101;
	  WriteAddress <= Instruccion[5:3];
	  ReadAddressA <= Instruccion[5:3];
	  ReadAddressB <= 3'bzzz;
	  Fun          <= 4'b0111;
       end
       S25: begin
	  EstadoFuturo <= S26;
	  Control      <= 6'b001000;
	  LoadSelect   <= 11'bzzzz_zzz_z1zz;
	  WriteAddress <= 3'bzzz;
	  ReadAddressA <= 3'bzzz;
	  ReadAddressB <= 3'bzzz;
	  Fun          <= 4'bzzzz;
       end
       S26: begin
	  EstadoFuturo <= SF1;
	  Control      <= 6'bzzz_zzz;
	  LoadSelect   <= 11'bzzzz_001_zzzz;
	  WriteAddress <= 3'bzzz;
	  ReadAddressA <= 3'bzzz;
	  ReadAddressB <= 3'bzzz;
	  Fun          <= 4'bzzzz;
       end
       S27: begin
	  EstadoFuturo <= S28;
	  Control      <= 6'b100010;
	  LoadSelect   <= 11'bzz11_zzz_z101;
	  WriteAddress <= Instruccion[5:3];
	  ReadAddressA <= Instruccion[5:3];
	  ReadAddressB <= 3'bzzz;
	  Fun          <= 4'b0100;
       end
       S28: begin
	  EstadoFuturo <= SF1;
	  Control      <= 6'bzzz_zzz;
	  LoadSelect   <= 11'bzzzz_001_zzzz;
	  WriteAddress <= 3'bzzz;
	  ReadAddressA <= 3'bzzz;
	  ReadAddressB <= 3'bzzz;
	  Fun          <= 4'bzzzz;
       end
     endcase // case (EstadoPresente)
   

   
endmodule // UnidadDeControl

ld2ud/code/ciscud/UnidadDeControl_Lab.v
module UnidadDeControl_Lab (/*AUTOARG*/
   // Outputs
   Instruccion, Reloj, Reiniciar
   ) ;
   output reg [15:0] Instruccion;
   output reg Reloj, Reiniciar;

   wire [5:0] Rta_Control;
   /* -----\/----- EXCLUDED -----\/-----
    
    wire 	    LoadS;
    wire [1:0] SelectS;
    wire 	    NegS;
    -----/\----- EXCLUDED -----/\----- */
   

//intentando lo que con tipo reg no
   wire       Rta_SelectDR, Rta_LoadDR;
   wire       Rta_SelectAR, Rta_LoadAR;
   
   wire [1:0] Rta_SelectPC;
   wire       Rta_LoadPC;
   
   wire       Rta_LoadIR, Rta_LoadCR;
   
   wire       Rta_WriteSelect, Rta_WriteEnable;
//hasta aqui lo que compone LoadSelect

   wire   [10:0] Rta_LoadSelect;
   
   wire [2:0] Rta_WriteAddress, Rta_ReadAddressA, Rta_ReadAddressB;
   
   wire [3:0] Rta_Fun;

   reg   [2:0] Rd, Rf1, Rf2;
   
   
   UnidadDeControl UC (Rta_Control,
		       Rta_LoadSelect,
		       Rta_WriteAddress,
		       Rta_ReadAddressA,
		       Rta_ReadAddressB,
		       Rta_Fun,
		       //Los estimulos de prueba:
		       Instruccion,Reloj,Reiniciar);

   assign Rta_LoadSelect = {Rta_SelectDR,Rta_LoadDR,
                        Rta_SelectAR,Rta_LoadAR,
                        Rta_SelectPC,Rta_LoadPC,
                        Rta_LoadIR,Rta_LoadCR,
                        Rta_WriteSelect,Rta_WriteEnable};

   initial begin
      Reloj = 1'b0;
      Reiniciar = 1'b1;
      Instruccion <= 16'h0;
      Rd <= 3'b000;
      Rf1 <= 3'b001;
      Rf2 <= 3'b010;
   end

   initial begin
      repeat (64) begin
	 #1 Reloj <=  ~Reloj;
      end
   end
   
   initial begin
      repeat (34) begin
	 #1 Reiniciar <= ~Reiniciar;
	 #11 Reiniciar <= ~Reiniciar;
      end
   end

   initial begin
      repeat (34) begin
	 #12 Rd <= Rd+3;
         Rf1 <= Rf1+3;
	 Rf2 <= Rf2+3;
      end
   end
   
   initial begin
      #12 Instruccion <= {7'h3,Rd,Rf1,Rf2};
      #12 Instruccion <= {7'h5,Rd,Rf1,Rf2};
      #12 Instruccion <= {7'h7,Rd,Rf1,Rf2};
   end

 
   initial begin
      $dumpfile("UnidadDeControl_Lab.vcd");
      $dumpvars;
   end
   
endmodule // UnidadDeControl_Lab

ld2ud/code/ciscud/UnidadDeControl_Lab.vcd
$date
	Wed Dec  9 10:36:52 2009
$end
$version
	Icarus Verilog
$end
$timescale
	1s
$end
$scope module UnidadDeControl_Lab $end
$var wire 6 ! Rta_Control[5:0] $end
$var wire 4 " Rta_Fun[3:0] $end
$var wire 1 # Rta_LoadAR $end
$var wire 1 $ Rta_LoadCR $end
$var wire 1 % Rta_LoadDR $end
$var wire 1 & Rta_LoadIR $end
$var wire 1 ' Rta_LoadPC $end
$var wire 11 ( Rta_LoadSelect[10:0] $end
$var wire 3 ) Rta_ReadAddressA[2:0] $end
$var wire 3 * Rta_ReadAddressB[2:0] $end
$var wire 1 + Rta_SelectAR $end
$var wire 1 , Rta_SelectDR $end
$var wire 2 - Rta_SelectPC[1:0] $end
$var wire 3 . Rta_WriteAddress[2:0] $end
$var wire 1 / Rta_WriteEnable $end
$var wire 1 0 Rta_WriteSelect $end
$var reg 16 1 Instruccion[15:0] $end
$var reg 3 2 Rd[2:0] $end
$var reg 1 3 Reiniciar $end
$var reg 1 4 Reloj $end
$var reg 3 5 Rf1[2:0] $end
$var reg 3 6 Rf2[2:0] $end
$scope module UC $end
$var wire 16 7 Instruccion[15:0] $end
$var wire 1 3 Reiniciar $end
$var wire 1 4 Reloj $end
$var reg 6 8 Control[5:0] $end
$var reg 7 9 EstadoFuturo[6:0] $end
$var reg 7 : EstadoPresente[6:0] $end
$var reg 4 ; Fun[3:0] $end
$var reg 11 < LoadSelect[10:0] $end
$var reg 3 = ReadAddressA[2:0] $end
$var reg 3 > ReadAddressB[2:0] $end
$var reg 3 ? WriteAddress[2:0] $end
$upscope $end
$upscope $end
$enddefinitions $end
#0
$dumpvars
bx ?
bx >
bx =
bx <
bx ;
bx :
b0 9
bx 8
b0 7
b10 6
b1 5
04
13
b0 2
b0 1
x0
x/
bx .
bx -
x,
x+
bx *
bx )
bx (
x'
x&
x%
x$
x#
bx "
bx !
$end
#1
bz "
bz ;
bz *
bz >
bz )
bz =
bz .
bz ?
z,
z%
z+
z#
bz -
z'
z&
1$
z0
bz1zz (
z/
bz1zz <
b100100 !
b100100 8
b1 9
b0 :
03
14
#2
04
#3
b11 -
1'
1&
z$
bz1111zzz (
bz1111zzz <
bz !
bz 8
b10 9
b1 :
14
#4
04
#5
b11 9
b10 :
14
#6
04
#7
b0 "
b0 ;
b0 *
b0 >
b0 )
b0 =
b0 .
b0 ?
bz -
z'
z&
00
bz01 (
1/
bz01 <
b0 9
b11 :
14
#8
04
#9
bz "
bz ;
bz *
bz >
bz )
bz =
bz .
bz ?
1$
z0
bz1zz (
z/
bz1zz <
b100100 !
b100100 8
b1 9
b0 :
14
#10
04
#11
b11 -
1'
1&
z$
bz1111zzz (
bz1111zzz <
bz !
bz 8
b10 9
b1 :
14
#12
b0 9
04
13
b11000001010 1
b11000001010 7
b101 6
b100 5
b11 2
#13
bz -
z'
z&
1$
bz1zz (
bz1zz <
b100100 !
b100100 8
b1 9
b0 :
14
03
#14
04
#15
b11 -
1'
1&
z$
bz1111zzz (
bz1111zzz <
bz !
bz 8
b10 9
b1 :
14
#16
04
#17
b11 9
b10 :
14
#18
04
#19
b11 "
b11 ;
b10 *
b10 >
b1 )
b1 =
b0 .
b0 ?
bz -
z'
z&
00
bz01 (
1/
bz01 <
b0 9
b11 :
14
#20
04
#21
bz "
bz ;
bz *
bz >
bz )
bz =
bz .
bz ?
1$
z0
bz1zz (
z/
bz1zz <
b100100 !
b100100 8
b1 9
b0 :
14
#22
04
#23
b11 -
1'
1&
z$
bz1111zzz (
bz1111zzz <
bz !
bz 8
b10 9
b1 :
14
#24
b0 9
04
13
b101011100101 1
b101011100101 7
b0 6
b111 5
b110 2
#25
bz -
z'
z&
1$
bz1zz (
bz1zz <
b100100 !
b100100 8
b1 9
b0 :
14
03
#26
04
#27
b11 -
1'
1&
z$
bz1111zzz (
bz1111zzz <
bz !
bz 8
b10 9
b1 :
14
#28
04
#29
b100 9
b10 :
14
#30
04
#31
b101 "
b101 ;
b101 *
b101 >
b100 )
b100 =
b11 .
b11 ?
bz -
z'
z&
00
bz01 (
1/
bz01 <
b0 9
b100 :
14
#32
04
#33
bz "
bz ;
bz *
bz >
bz )
bz =
bz .
bz ?
1$
z0
bz1zz (
z/
bz1zz <
b100100 !
b100100 8
b1 9
b0 :
14
#34
04
#35
b11 -
1'
1&
z$
bz1111zzz (
bz1111zzz <
bz !
bz 8
b10 9
b1 :
14
#36
b0 9
04
13
b111110111000 1
b111110111000 7
b11 6
b10 5
b1 2
#37
bz -
z'
z&
1$
bz1zz (
bz1zz <
b100100 !
b100100 8
b1 9
b0 :
14
03
#38
04
#39
b11 -
1'
1&
z$
bz1111zzz (
bz1111zzz <
bz !
bz 8
b10 9
b1 :
14
#40
04
#41
b100 9
b10 :
14
#42
04
#43
b111 "
b111 ;
b0 *
b0 >
b111 )
b111 =
b110 .
b110 ?
bz -
z'
z&
00
bz01 (
1/
bz01 <
b0 9
b100 :
14
#44
04
#45
bz "
bz ;
bz *
bz >
bz )
bz =
bz .
bz ?
1$
z0
bz1zz (
z/
bz1zz <
b100100 !
b100100 8
b1 9
b0 :
14
#46
04
#47
b11 -
1'
1&
z$
bz1111zzz (
bz1111zzz <
bz !
bz 8
b10 9
b1 :
14
#48
b0 9
04
13
b110 6
b101 5
b100 2
#49
bz -
z'
z&
1$
bz1zz (
bz1zz <
b100100 !
b100100 8
b1 9
b0 :
14
03
#50
04
#51
b11 -
1'
1&
z$
bz1111zzz (
bz1111zzz <
bz !
bz 8
b10 9
b1 :
14
#52
04
#53
b100 9
b10 :
14
#54
04
#55
b111 "
b111 ;
b0 *
b0 >
b111 )
b111 =
b110 .
b110 ?
bz -
z'
z&
00
bz01 (
1/
bz01 <
b0 9
b100 :
14
#56
04
#57
bz "
bz ;
bz *
bz >
bz )
bz =
bz .
bz ?
1$
z0
bz1zz (
z/
bz1zz <
b100100 !
b100100 8
b1 9
b0 :
14
#58
04
#59
b11 -
1'
1&
z$
bz1111zzz (
bz1111zzz <
bz !
bz 8
b10 9
b1 :
14
#60
b0 9
04
13
b1 6
b0 5
b111 2
#61
bz -
z'
z&
1$
bz1zz (
bz1zz <
b100100 !
b100100 8
b1 9
b0 :
14
03
#62
04
#63
b11 -
1'
1&
z$
bz1111zzz (
bz1111zzz <
bz !
bz 8
b10 9
b1 :
14
#64
04
#72
b0 9
13
b100 6
b11 5
b10 2
#73
03
#84
13
b111 6
b110 5
b101 2
#85
03
#96
13
b10 6
b1 5
b0 2
#97
03
#108
13
b101 6
b100 5
b11 2
#109
03
#120
13
b0 6
b111 5
b110 2
#121
03
#132
13
b11 6
b10 5
b1 2
#133
03
#144
13
b110 6
b101 5
b100 2
#145
03
#156
13
b1 6
b0 5
b111 2
#157
03
#168
13
b100 6
b11 5
b10 2
#169
03
#180
13
b111 6
b110 5
b101 2
#181
03
#192
13
b10 6
b1 5
b0 2
#193
03
#204
13
b101 6
b100 5
b11 2
#205
03
#216
13
b0 6
b111 5
b110 2
#217
03
#228
13
b11 6
b10 5
b1 2
#229
03
#240
13
b110 6
b101 5
b100 2
#241
03
#252
13
b1 6
b0 5
b111 2
#253
03
#264
13
b100 6
b11 5
b10 2
#265
03
#276
13
b111 6
b110 5
b101 2
#277
03
#288
13
b10 6
b1 5
b0 2
#289
03
#300
13
b101 6
b100 5
b11 2
#301
03
#312
13
b0 6
b111 5
b110 2
#313
03
#324
13
b11 6
b10 5
b1 2
#325
03
#336
13
b110 6
b101 5
b100 2
#337
03
#348
13
b1 6
b0 5
b111 2
#349
03
#360
13
b100 6
b11 5
b10 2
#361
03
#372
13
b111 6
b110 5
b101 2
#373
03
#384
13
b10 6
b1 5
b0 2
#385
03
#396
13
b101 6
b100 5
b11 2
#397
03
#408
13
b0 6
b111 5
b110 2
