misc/articulos/impvl/src/counter/semaforo.v
//-----------------------------------------------------------------------------
// Title         : Solucion al problema de los semaforos
// Project       : Laboratorios de Digitales I
//-----------------------------------------------------------------------------
// File          : semaforos.v
// Author        : Mauricio Velasquez Velasquez  <mvelasquez@lud.udistrita.edu.co>
// Created       : 26.10.2004
// Last modified : 26.10.2004
//-----------------------------------------------------------------------------
// Description :
// Implementacion del control para un semaforo utilizando pulsos de reloj.
//-----------------------------------------------------------------------------
// Copyright (c) 2004 by GLUD-electronica (Electronix) This model is the confidential and
// proprietary property of GLUD-electronica (Electronix) and the possession or use of this
// file requires a written license from GLUD-electronica (Electronix).
//------------------------------------------------------------------------------
// Modification history :
// 26.10.2004 : created
//-----------------------------------------------------------------------------


module luces_semaforo;
    reg
         clock,
         rojo,
         amarillo,
         verde;
    parameter
         on = 1,
         off = 0,
         rojo_tics = 35,
         amarillo_tics = 3,
         verde_tics = 20;
    // Secuencia de control de las luces
    always
         begin
           rojo = on;
           amarillo = off;
           verde = off;
           repeat (rojo_tics) @(posedge clock);
           rojo = off;
           verde = on;
           repeat (verde_tics) @(posedge clock);
           verde = off;
           amarillo = on;
           repeat (amarillo_tics) @(posedge clock);
         end
    // Forma de onda para el clock
   always
      begin
         #10 clock = 0;
         #10 clock = 1;
         end
   // DescripciOn para la simulaciOn para 10 cambios de la luz roja 
   initial
     begin
        repeat (10) @rojo;
        $finish;
     end
   // Muestra el tiempo y el cambio de estado de las luces
   always begin
         @(rojo or amarillo or verde)
      $display("%d rojo=%b amarillo=%b verde=%b",
               $time, rojo, amarillo, verde);
   $dumpfile ("semaforo.vcd"); // Creacion del archivo de Simulacion
   // $dumpvars;
end 
endmodule

misc/articulos/impvl/src/counter/semaforo.vcd
$date
	Fri Nov  5 14:58:29 2004
$end
$version
	Icarus Verilog
$end
$timescale
	1s
$end
$scope module luces_semaforo $end
$var reg 1 ! amarillo $end
$var reg 1 " clock $end
$var reg 1 # rojo $end
$var reg 1 $ verde $end
$upscope $end
$enddefinitions $end
#70
$dumpvars
1$
0#
1"
0!
$end
#71
0"
#72
1"
#73
0"
#74
1"
#75
0"
#76
1"
#77
0"
#78
1"
#79
0"
#80
1"
#81
0"
#82
1"
#83
0"
#84
1"
#85
0"
#86
1"
#87
0"
#88
1"
#89
0"
#90
1"
#91
0"
#92
1"
#93
0"
#94
1"
#95
0"
#96
1"
#97
0"
#98
1"
#99
0"
#100
1"
#101
0"
#102
1"
#103
0"
#104
1"
#105
0"
#106
1"
#107
0"
#108
1"
#109
0"
#110
1!
0$
1"
#111
0"
#112
1"
#113
0"
#114
1"
#115
0"
#116
0!
1#
1"
#117
0"
#118
1"
#119
0"
#120
1"
#121
0"
#122
1"
#123
0"
#124
1"
#125
0"
#126
1"
#127
0"
#128
1"
#129
0"
#130
1"
#131
0"
#132
1"
#133
0"
#134
1"
#135
0"
#136
1"
#137
0"
#138
1"
#139
0"
#140
1"
#141
0"
#142
1"
#143
0"
#144
1"
#145
0"
#146
1"
#147
0"
#148
1"
#149
0"
#150
1"
#151
0"
#152
1"
#153
0"
#154
1"
#155
0"
#156
1"
#157
0"
#158
1"
#159
0"
#160
1"
#161
0"
#162
1"
#163
0"
#164
1"
#165
0"
#166
1"
#167
0"
#168
1"
#169
0"
#170
1"
#171
0"
#172
1"
#173
0"
#174
1"
#175
0"
#176
1"
#177
0"
#178
1"
#179
0"
#180
1"
#181
0"
#182
1"
#183
0"
#184
1"
#185
0"
#186
1$
0#
1"
#187
0"
#188
1"
#189
0"
#190
1"
#191
0"
#192
1"
#193
0"
#194
1"
#195
0"
#196
1"
#197
0"
#198
1"
#199
0"
#200
1"
#201
0"
#202
1"
#203
0"
#204
1"
#205
0"
#206
1"
#207
0"
#208
1"
#209
0"
#210
1"
#211
0"
#212
1"
#213
0"
#214
1"
#215
0"
#216
1"
#217
0"
#218
1"
#219
0"
#220
1"
#221
0"
#222
1"
#223
0"
#224
1"
#225
0"
#226
1!
0$
1"
#227
0"
#228
1"
#229
0"
#230
1"
#231
0"
#232
0!
1#
1"
#233
0"
#234
1"
#235
0"
#236
1"
#237
0"
#238
1"
#239
0"
#240
1"
#241
0"
#242
1"
#243
0"
#244
1"
#245
0"
#246
1"
#247
0"
#248
1"
#249
0"
#250
1"
#251
0"
#252
1"
#253
0"
#254
1"
#255
0"
#256
1"
#257
0"
#258
1"
#259
0"
#260
1"
#261
0"
#262
1"
#263
0"
#264
1"
#265
0"
#266
1"
#267
0"
#268
1"
#269
0"
#270
1"
#271
0"
#272
1"
#273
0"
#274
1"
#275
0"
#276
1"
#277
0"
#278
1"
#279
0"
#280
1"
#281
0"
#282
1"
#283
0"
#284
1"
#285
0"
#286
1"
#287
0"
#288
1"
#289
0"
#290
1"
#291
0"
#292
1"
#293
0"
#294
1"
#295
0"
#296
1"
#297
0"
#298
1"
#299
0"
#300
1"
#301
0"
#302
1$
0#
1"
#303
0"
#304
1"
#305
0"
#306
1"
#307
0"
#308
1"
#309
0"
#310
1"
#311
0"
#312
1"
#313
0"
#314
1"
#315
0"
#316
1"
#317
0"
#318
1"
#319
0"
#320
1"
#321
0"
#322
1"
#323
0"
#324
1"
#325
0"
#326
1"
#327
0"
#328
1"
#329
0"
#330
1"
#331
0"
#332
1"
#333
0"
#334
1"
#335
0"
#336
1"
#337
0"
#338
1"
#339
0"
#340
1"
#341
0"
#342
1!
0$
1"
#343
0"
#344
1"
#345
0"
#346
1"
#347
0"
#348
0!
1#
1"
