trunk/ld2ud/code/CombinatoriaCodigo.v
module CombinatoriaCodigo (/*AUTOARG*/
   // Outputs
   Salida,
   // Inputs
   Entrada
   ) ;
   output Salida;
   input  [5:0] Entrada;

   wire   [21:0] Nodo;
   
   and (Nodo[21],~Entrada[5],~Entrada[4],~Entrada[3],~Entrada[2],~Entrada[1],Entrada[0]);
   and (Nodo[20],~Entrada[5],~Entrada[4],~Entrada[3],~Entrada[2],Entrada[1],~Entrada[0]);
   and (Nodo[19],~Entrada[5],~Entrada[4],~Entrada[3],~Entrada[2],Entrada[1],Entrada[0]);
   and (Nodo[18],~Entrada[5],~Entrada[4],~Entrada[3],Entrada[2],~Entrada[1],Entrada[0]);
   and (Nodo[17],~Entrada[5],~Entrada[4],Entrada[3],~Entrada[2],Entrada[1],~Entrada[0]);
   and (Nodo[16],~Entrada[5],~Entrada[4],Entrada[3],Entrada[2],~Entrada[1],~Entrada[0]);
   and (Nodo[15],~Entrada[5],~Entrada[4],Entrada[3],Entrada[2],~Entrada[1],Entrada[0]);
   and (Nodo[14],~Entrada[5],~Entrada[4],Entrada[3],Entrada[2],Entrada[1],Entrada[0]);
   and (Nodo[13],~Entrada[5],Entrada[4],~Entrada[3],Entrada[2],~Entrada[1],~Entrada[0]);
   and (Nodo[12],~Entrada[5],Entrada[4],~Entrada[3],Entrada[2],~Entrada[1],Entrada[0]);
   and (Nodo[11],~Entrada[5],Entrada[4],~Entrada[3],Entrada[2],Entrada[1],~Entrada[0]);
   and (Nodo[10],~Entrada[5],Entrada[4],~Entrada[3],Entrada[2],Entrada[1],Entrada[0]);
   and (Nodo[9],~Entrada[5],Entrada[4],Entrada[3],~Entrada[2],~Entrada[1],Entrada[0]);
   and (Nodo[8],~Entrada[5],Entrada[4],Entrada[3],Entrada[2],Entrada[1],~Entrada[0]);
   and (Nodo[7],~Entrada[5],Entrada[4],Entrada[3],Entrada[2],Entrada[1],Entrada[0]);
   and (Nodo[6],Entrada[5],~Entrada[4],~Entrada[3],~Entrada[2],~Entrada[1],~Entrada[0]);
   and (Nodo[5],Entrada[5],~Entrada[4],~Entrada[3],~Entrada[2],~Entrada[1],Entrada[0]);
   and (Nodo[4],Entrada[5],~Entrada[4],~Entrada[3],~Entrada[2],Entrada[1],Entrada[0]);
   and (Nodo[3],Entrada[5],Entrada[4],~Entrada[3],~Entrada[2],Entrada[1],~Entrada[0]);
   and (Nodo[2],Entrada[5],Entrada[4],~Entrada[3],~Entrada[2],Entrada[1],Entrada[0]);
   and (Nodo[1],Entrada[5],Entrada[4],~Entrada[3],Entrada[2],~Entrada[1],~Entrada[0]);
   and (Nodo[0],Entrada[5],Entrada[4],~Entrada[3],Entrada[2],~Entrada[1],Entrada[0]);

   or (Salida,Nodo[0],Nodo[1],Nodo[2],Nodo[3],Nodo[4],Nodo[5],Nodo[6],Nodo[7],Nodo[8],Nodo[9],Nodo[10],Nodo[11],Nodo[12],Nodo[13],Nodo[14],Nodo[15],Nodo[16],Nodo[17],Nodo[18],Nodo[19],Nodo[20],Nodo[21]);
   
   
endmodule // CombinatoriaCodigo

trunk/ld2ud/code/MayorQue63.v
module MayorQue63 (/*AUTOARG*/
   // Outputs
   Salida,
   // Inputs
   Entrada
   ) ;
   //Revisa si un número natural menor a 100 es mayor que 63
   //Es mayor si el bit 7 es uno :)
   output Salida;
   input  [6:0] Entrada;

//si bit 7 = 1 => 63, como para mayores de 63 piden 0 en la salida solo hay que negar el bit
   assign Salida = ~Entrada[6];
   
endmodule // MayorQue63
//tags: laboratorio

trunk/ld2ud/code/Laboratorio2_Lab.v
module Laboratorio2_Lab (/*AUTOARG*/ ) ;
   reg   [6:0] Combinacion2Digitos;
   reg [5:0]   Estimulo;
 	       
   MayorQue63 U1 (RtaMayorQue63,Combinacion2Digitos);
   
   CombinatoriaCodigo U2 (RtaCombinatoriaCodigo,Estimulo[5:0]);
   
   
   initial begin
      Combinacion2Digitos = 7'b0000000;
      Estimulo = 6'b000000;
      
   end

   initial begin
      
      repeat (100) begin
	 #1 Combinacion2Digitos <= Combinacion2Digitos + 1;
	 
      end
   end

   initial begin
      repeat (62) begin
	 #1 Estimulo <= Estimulo + 1;
	 
      end

   end
   

   initial begin
      $dumpfile ("Laboratorio2_Lab.vcd");
      $dumpvars;
   end
   
   
endmodule // Laboratorio2_Lab

trunk/ld2ud/code/Laboratorio2_Lab.vcd
$date
	Tue Sep 29 14:03:08 2009
$end
$version
	Icarus Verilog
$end
$timescale
	1s
$end
$scope module Laboratorio2_Lab $end
$var wire 1 ! RtaMayorQue63 $end
$var wire 1 " RtaCombinatoriaCodigo $end
$var reg 7 # Combinacion2Digitos[6:0] $end
$var reg 6 $ Estimulo[5:0] $end
$scope module U1 $end
$var wire 7 % Entrada[6:0] $end
$var wire 1 ! Salida $end
$upscope $end
$scope module U2 $end
$var wire 6 & Entrada[5:0] $end
$var wire 22 ' Nodo[21:0] $end
$var wire 1 " Salida $end
$upscope $end
$upscope $end
$enddefinitions $end
#0
$dumpvars
b0 '
b0 &
b0 %
b0 $
b0 #
0"
1!
$end
#1
1"
b1000000000000000000000 '
b1 $
b1 &
b1 #
b1 %
#2
b100000000000000000000 '
b10 $
b10 &
b10 #
b10 %
#3
b10000000000000000000 '
b11 $
b11 &
b11 #
b11 %
#4
0"
b0 '
b100 $
b100 &
b100 #
b100 %
#5
1"
b1000000000000000000 '
b101 $
b101 &
b101 #
b101 %
#6
0"
b0 '
b110 $
b110 &
b110 #
b110 %
#7
b111 $
b111 &
b111 #
b111 %
#8
b1000 $
b1000 &
b1000 #
b1000 %
#9
b1001 $
b1001 &
b1001 #
b1001 %
#10
1"
b100000000000000000 '
b1010 $
b1010 &
b1010 #
b1010 %
#11
0"
b0 '
b1011 $
b1011 &
b1011 #
b1011 %
#12
1"
b10000000000000000 '
b1100 $
b1100 &
b1100 #
b1100 %
#13
b1000000000000000 '
b1101 $
b1101 &
b1101 #
b1101 %
#14
0"
b0 '
b1110 $
b1110 &
b1110 #
b1110 %
#15
1"
b100000000000000 '
b1111 $
b1111 &
b1111 #
b1111 %
#16
0"
b0 '
b10000 $
b10000 &
b10000 #
b10000 %
#17
b10001 $
b10001 &
b10001 #
b10001 %
#18
b10010 $
b10010 &
b10010 #
b10010 %
#19
b10011 $
b10011 &
b10011 #
b10011 %
#20
1"
b10000000000000 '
b10100 $
b10100 &
b10100 #
b10100 %
#21
b1000000000000 '
b10101 $
b10101 &
b10101 #
b10101 %
#22
b100000000000 '
b10110 $
b10110 &
b10110 #
b10110 %
#23
b10000000000 '
b10111 $
b10111 &
b10111 #
b10111 %
#24
0"
b0 '
b11000 $
b11000 &
b11000 #
b11000 %
#25
1"
b1000000000 '
b11001 $
b11001 &
b11001 #
b11001 %
#26
0"
b0 '
b11010 $
b11010 &
b11010 #
b11010 %
#27
b11011 $
b11011 &
b11011 #
b11011 %
#28
b11100 $
b11100 &
b11100 #
b11100 %
#29
b11101 $
b11101 &
b11101 #
b11101 %
#30
1"
b100000000 '
b11110 $
b11110 &
b11110 #
b11110 %
#31
b10000000 '
b11111 $
b11111 &
b11111 #
b11111 %
#32
1"
b1000000 '
b100000 $
b100000 &
b100000 #
b100000 %
#33
b100000 '
b100001 $
b100001 &
b100001 #
b100001 %
#34
0"
b0 '
b100010 $
b100010 &
b100010 #
b100010 %
#35
1"
b10000 '
b100011 $
b100011 &
b100011 #
b100011 %
#36
0"
b0 '
b100100 $
b100100 &
b100100 #
b100100 %
#37
b100101 $
b100101 &
b100101 #
b100101 %
#38
b100110 $
b100110 &
b100110 #
b100110 %
#39
b100111 $
b100111 &
b100111 #
b100111 %
#40
b101000 $
b101000 &
b101000 #
b101000 %
#41
b101001 $
b101001 &
b101001 #
b101001 %
#42
b101010 $
b101010 &
b101010 #
b101010 %
#43
b101011 $
b101011 &
b101011 #
b101011 %
#44
b101100 $
b101100 &
b101100 #
b101100 %
#45
b101101 $
b101101 &
b101101 #
b101101 %
#46
b101110 $
b101110 &
b101110 #
b101110 %
#47
b101111 $
b101111 &
b101111 #
b101111 %
#48
b110000 $
b110000 &
b110000 #
b110000 %
#49
b110001 $
b110001 &
b110001 #
b110001 %
#50
1"
b1000 '
b110010 $
b110010 &
b110010 #
b110010 %
#51
b100 '
b110011 $
b110011 &
b110011 #
b110011 %
#52
1"
b10 '
b110100 $
b110100 &
b110100 #
b110100 %
#53
b1 '
b110101 $
b110101 &
b110101 #
b110101 %
#54
0"
b0 '
b110110 $
b110110 &
b110110 #
b110110 %
#55
b110111 $
b110111 &
b110111 #
b110111 %
#56
b111000 $
b111000 &
b111000 #
b111000 %
#57
b111001 $
b111001 &
b111001 #
b111001 %
#58
b111010 $
b111010 &
b111010 #
b111010 %
#59
b111011 $
b111011 &
b111011 #
b111011 %
#60
b111100 $
b111100 &
b111100 #
b111100 %
#61
b111101 $
b111101 &
b111101 #
b111101 %
#62
b111110 $
b111110 &
b111110 #
b111110 %
#63
b111111 #
b111111 %
#64
0!
b1000000 #
b1000000 %
#65
b1000001 #
b1000001 %
#66
b1000010 #
b1000010 %
#67
b1000011 #
b1000011 %
#68
b1000100 #
b1000100 %
#69
b1000101 #
b1000101 %
#70
b1000110 #
b1000110 %
#71
b1000111 #
b1000111 %
#72
b1001000 #
b1001000 %
#73
b1001001 #
b1001001 %
#74
b1001010 #
b1001010 %
#75
b1001011 #
b1001011 %
#76
b1001100 #
b1001100 %
#77
b1001101 #
b1001101 %
#78
b1001110 #
b1001110 %
#79
b1001111 #
b1001111 %
#80
b1010000 #
b1010000 %
#81
b1010001 #
b1010001 %
#82
b1010010 #
b1010010 %
#83
b1010011 #
b1010011 %
#84
b1010100 #
b1010100 %
#85
b1010101 #
b1010101 %
#86
b1010110 #
b1010110 %
#87
b1010111 #
b1010111 %
#88
b1011000 #
b1011000 %
#89
b1011001 #
b1011001 %
#90
b1011010 #
b1011010 %
#91
b1011011 #
b1011011 %
#92
b1011100 #
b1011100 %
#93
b1011101 #
b1011101 %
#94
b1011110 #
b1011110 %
#95
b1011111 #
b1011111 %
#96
b1100000 #
b1100000 %
#97
b1100001 #
b1100001 %
#98
b1100010 #
b1100010 %
#99
b1100011 #
b1100011 %
#100
b1100100 #
b1100100 %
