trunk/ld2ud/code/Multiplexor4a1.v
module Multiplexor4a1 (/*AUTOARG*/
   // Outputs
   Salida,
   // Inputs
   Selector, Entrada
   ) ;
   output Salida;
   input  [1:0] Selector;
   input  [3:0] Entrada;

   wire   [3:0] BusOr;

   and AndUno (BusOr[3],Entrada[3],~Selector[1],~Selector[0]);
   and AndDos (BusOr[2],Entrada[2],~Selector[1],Selector[0]);   
   and AndTres (BusOr[1],Entrada[1],Selector[1],~Selector[0]);   
   and AndCuatro (BusOr[0],Entrada[0],Selector[1],Selector[0]);

   or (Salida,BusOr[3],BusOr[2],BusOr[1],BusOr[0]);
   
   
endmodule // Multiplexor4a1


// referencia http://www.see.ed.ac.uk/~gerard/Teach/Verilog/manual/Example/lrgeEx1/intro.html

trunk/ld2ud/code/Decodificador3a8.v
module Decodificador3a8 (/*AUTOARG*/
   // Outputs
   Salida,
   // Inputs
   Entrada
   ) ;
   output [7:0] Salida;
   input  [2:0] Entrada;

   and (Salida[0],Entrada[2],Entrada[1],Entrada[0]);
   and (Salida[1],Entrada[2],Entrada[1],~Entrada[0]);
   and (Salida[2],Entrada[2],~Entrada[1],Entrada[0]);
   and (Salida[3],Entrada[2],~Entrada[1],~Entrada[0]);
   and (Salida[4],~Entrada[2],Entrada[1],Entrada[0]);
   and (Salida[5],~Entrada[2],Entrada[1],~Entrada[0]);
   and (Salida[6],~Entrada[2],~Entrada[1],Entrada[0]);
   and (Salida[7],~Entrada[2],~Entrada[1],~Entrada[0]);   
   
endmodule // Decodificador3a8

ld2ud/code/Comparador22Numeros6Bit_Multiplexor.v
module Comparador22Numeros6Bit_Multiplexor (/*AUTOARG*/
   // Outputs
   Salida,
   // Inputs
   Entrada
   ) ;
   output Salida;
   input  [5:0] Entrada;

   wire   [3:0] BusMultiplexor;

   and (BusMultiplexor[0], ~Entrada[3], ~Entrada[2], ~Entrada[1], Entrada[0]);
   and (BusMultiplexor[0], ~Entrada[3], ~Entrada[2], Entrada[1], ~Entrada[0]);
   and (BusMultiplexor[0], ~Entrada[3], ~Entrada[2], Entrada[1], Entrada[0]);
   and (BusMultiplexor[0], ~Entrada[3], Entrada[2], ~Entrada[1], Entrada[0]);
   and (BusMultiplexor[0], Entrada[3], ~Entrada[2], Entrada[1], ~Entrada[0]);
   and (BusMultiplexor[0], Entrada[3], Entrada[2], ~Entrada[1], ~Entrada[0]);
   and (BusMultiplexor[0], Entrada[3], Entrada[2], ~Entrada[1], Entrada[0]);
   and (BusMultiplexor[0], Entrada[3], Entrada[2], Entrada[1], Entrada[0]);
   and (BusMultiplexor[1], ~Entrada[3], Entrada[2], ~Entrada[1], ~Entrada[0]);
   and (BusMultiplexor[1], ~Entrada[3], Entrada[2], ~Entrada[1], Entrada[0]);
   and (BusMultiplexor[1], ~Entrada[3], Entrada[2], Entrada[1], ~Entrada[0]);
   and (BusMultiplexor[1], ~Entrada[3], Entrada[2], Entrada[1], Entrada[0]);
   and (BusMultiplexor[1], Entrada[3], ~Entrada[2], ~Entrada[1], Entrada[0]);
   and (BusMultiplexor[1], Entrada[3], Entrada[2], Entrada[1], ~Entrada[0]);
   and (BusMultiplexor[1], Entrada[3], Entrada[2], Entrada[1], Entrada[0]);
   and (BusMultiplexor[2], ~Entrada[3], Entrada[2], ~Entrada[1], ~Entrada[0]);
   and (BusMultiplexor[2], ~Entrada[3], ~Entrada[2], ~Entrada[1], Entrada[0]);
   and (BusMultiplexor[2], ~Entrada[3], ~Entrada[2], Entrada[1], Entrada[0]);
   and (BusMultiplexor[3], ~Entrada[3], ~Entrada[2], Entrada[1], ~Entrada[0]);
   and (BusMultiplexor[3], ~Entrada[3], ~Entrada[2], Entrada[1], Entrada[0]);
   and (BusMultiplexor[3], ~Entrada[3], Entrada[2], ~Entrada[1], ~Entrada[0]);
   and (BusMultiplexor[3], ~Entrada[3], Entrada[2], ~Entrada[1], Entrada[0]);

   
   Multiplexor4a1 U1 (Salida,Entrada[5:4],BusMultiplexor);

   
endmodule // Comparador22Numeros6Bit_Multiplexor

ld2ud/code/Comparador22Numeros6Bit_Decodificador.v
module Comparador22Numeros6Bit_Decodificador (/*AUTOARG*/
   // Outputs
   Salida,
   // Inputs
   Entrada
   ) ;
   output Salida;
   input  [5:0] Entrada;

   wire   [7:0] BusPar, BusImpar;
   wire   [21:0] BusOr;

   Decodificador3a8 U1 (BusPar[7:0],Entrada[5:3]);   
   Decodificador3a8 U2 (BusImpar[7:0],Entrada[2:0]);

   and (BusOr[0], BusPar[7], BusImpar[6]);
   and (BusOr[1], BusPar[7], BusImpar[5]);
   and (BusOr[2], BusPar[7], BusImpar[4]);
   and (BusOr[3], BusPar[7], BusImpar[2]);
   and (BusOr[4], BusPar[6], BusImpar[5]);
   and (BusOr[5], BusPar[6], BusImpar[3]);
   and (BusOr[6], BusPar[6], BusImpar[2]);
   and (BusOr[7], BusPar[6], BusImpar[0]);
   and (BusOr[8], BusPar[5], BusImpar[3]);
   and (BusOr[9], BusPar[5], BusImpar[2]);
   and (BusOr[10], BusPar[5], BusImpar[1]);
   and (BusOr[11], BusPar[5], BusImpar[0]);
   and (BusOr[12], BusPar[4], BusImpar[6]);
   and (BusOr[13], BusPar[4], BusImpar[1]);
   and (BusOr[14], BusPar[4], BusImpar[0]);
   and (BusOr[15], BusPar[3], BusImpar[7]);
   and (BusOr[16], BusPar[3], BusImpar[6]);
   and (BusOr[17], BusPar[3], BusImpar[4]);
   and (BusOr[18], BusPar[1], BusImpar[5]);
   and (BusOr[19], BusPar[1], BusImpar[4]);
   and (BusOr[20], BusPar[1], BusImpar[3]);
   and (BusOr[21], BusPar[1], BusImpar[2]);

   or (Salida,BusOr[0],BusOr[1],BusOr[2],BusOr[3],BusOr[4],BusOr[5],BusOr[6],BusOr[7],BusOr[8],BusOr[9],BusOr[10],BusOr[11],BusOr[12],BusOr[13],BusOr[14],BusOr[15],BusOr[16],BusOr[17],BusOr[18],BusOr[19],BusOr[20],BusOr[21]);
   
endmodule // Comparador22Numeros6bit_Decodificador

trunk/ld2ud/code/Comparador22Numeros6Bit_Compuertas.v
module Comparador22Numeros6Bit_Compuertas (/*AUTOARG*/
   // Para más info revisar APÉNDICE al final del archivo
   // Outputs
   Salida,
   // Inputs
   Entrada
   ) ;
   output Salida; //Es uno(1) si Entrada pertenece a conjunto Combinación
   input  [5:0] Entrada; //Número que se desea saber si pertenece a conjunto Combinación

   wire   [21:0] Nodo; //Nodo[x] es salida de cada decodificador básico
   
   and Dec01 (Nodo[21],~Entrada[5],~Entrada[4],~Entrada[3],~Entrada[2],~Entrada[1],Entrada[0]);
   and Dec02 (Nodo[20],~Entrada[5],~Entrada[4],~Entrada[3],~Entrada[2],Entrada[1],~Entrada[0]);
   and Dec03 (Nodo[19],~Entrada[5],~Entrada[4],~Entrada[3],~Entrada[2],Entrada[1],Entrada[0]);
   and Dec04 (Nodo[18],~Entrada[5],~Entrada[4],~Entrada[3],Entrada[2],~Entrada[1],Entrada[0]);
   and Dec04 (Nodo[17],~Entrada[5],~Entrada[4],Entrada[3],~Entrada[2],Entrada[1],~Entrada[0]);
   and Dec06 (Nodo[16],~Entrada[5],~Entrada[4],Entrada[3],Entrada[2],~Entrada[1],~Entrada[0]);
   and Dec07 (Nodo[15],~Entrada[5],~Entrada[4],Entrada[3],Entrada[2],~Entrada[1],Entrada[0]);
   and Dec08 (Nodo[14],~Entrada[5],~Entrada[4],Entrada[3],Entrada[2],Entrada[1],Entrada[0]);
   and Dec09 (Nodo[13],~Entrada[5],Entrada[4],~Entrada[3],Entrada[2],~Entrada[1],~Entrada[0]);
   and Dec10 (Nodo[12],~Entrada[5],Entrada[4],~Entrada[3],Entrada[2],~Entrada[1],Entrada[0]);
   and Dec11 (Nodo[11],~Entrada[5],Entrada[4],~Entrada[3],Entrada[2],Entrada[1],~Entrada[0]);
   and Dec12 (Nodo[10],~Entrada[5],Entrada[4],~Entrada[3],Entrada[2],Entrada[1],Entrada[0]);
   and Dec13 (Nodo[9],~Entrada[5],Entrada[4],Entrada[3],~Entrada[2],~Entrada[1],Entrada[0]);
   and Dec14 (Nodo[8],~Entrada[5],Entrada[4],Entrada[3],Entrada[2],Entrada[1],~Entrada[0]);
   and Dec15 (Nodo[7],~Entrada[5],Entrada[4],Entrada[3],Entrada[2],Entrada[1],Entrada[0]);
   and Dec16 (Nodo[6],Entrada[5],~Entrada[4],~Entrada[3],~Entrada[2],~Entrada[1],~Entrada[0]);
   and Dec17 (Nodo[5],Entrada[5],~Entrada[4],~Entrada[3],~Entrada[2],~Entrada[1],Entrada[0]);
   and Dec18 (Nodo[4],Entrada[5],~Entrada[4],~Entrada[3],~Entrada[2],Entrada[1],Entrada[0]);
   and Dec19 (Nodo[3],Entrada[5],Entrada[4],~Entrada[3],~Entrada[2],Entrada[1],~Entrada[0]);
   and Dec20 (Nodo[2],Entrada[5],Entrada[4],~Entrada[3],~Entrada[2],Entrada[1],Entrada[0]);
   and Dec21 (Nodo[1],Entrada[5],Entrada[4],~Entrada[3],Entrada[2],~Entrada[1],~Entrada[0]);
   and Dec22 (Nodo[0],Entrada[5],Entrada[4],~Entrada[3],Entrada[2],~Entrada[1],Entrada[0]);

   or (Salida,Nodo[0],Nodo[1],Nodo[2],Nodo[3],Nodo[4],Nodo[5],Nodo[6],Nodo[7],Nodo[8],Nodo[9],Nodo[10],Nodo[11],Nodo[12],Nodo[13],Nodo[14],Nodo[15],Nodo[16],Nodo[17],Nodo[18],Nodo[19],Nodo[20],Nodo[21]);
   
   
endmodule // Comparador22Numeros6Bit_Compuertas


/* APÉNDICE
 * Tenemos el conjunto Combinación que contiene 22 números diferentes de 6 bit
 * y deseamos que cuando Entrada pertenezca al conjunto Combinación Salida sea uno(1)
 *
 * Combinación  Binario  Salida
 * 01      	000_001       1
 * 02      	000_010       1
 * 03      	000_011       1
 * 05      	000_101       1
 * 10      	001_010       1
 * 12      	001_100       1
 * 13      	001_101       1
 * 15      	001_111       1
 * 20      	010_100       1
 * 21      	010_101       1
 * 22      	010_110       1
 * 23      	010_111       1
 * 25      	011_001       1
 * 30      	011_110       1
 * 31      	011_111       1
 * 32      	100_000       1
 * 33      	100_001       1
 * 35      	100_011       1
 * 50      	110_010       1
 * 51      	110_011       1
 * 52      	110_100       1
 * 53      	110_101       1
 *
 * Este módulo implementa un decodificador binario básico (Referencia:Fundamentos de 
 * Sistemas Digitales,edición 7,pág 350,Thomas L. Floyd) llamado DecXX para cada elemento
 * del conjunto Combinación y la salida de los 22 DecXX (Nodo[x]) entra en una compuerta or.
 */

trunk/ld2ud/code/Laboratorio2_Lab.v
module Laboratorio2_Lab (/*AUTOARG*/ ) ;
   wire   RtaComparador22Numeros6Bit_Compuertas;
   wire   RtaComparador22Numeros6Bit_Decodificador ;
   wire   RtaComparador22Numeros6Bit_Multiplexor;
   wire   [7:0] RtaDecodificador3a8;
   
   reg [5:0]   Estimulo;
   reg   [2:0] EstimuloDecodificador3a8;


   Comparador22Numeros6Bit_Compuertas U1 (RtaComparador22Numeros6Bit_Compuertas,Estimulo[5:0]);
   Comparador22Numeros6Bit_Decodificador U2 (RtaComparador22Numeros6Bit_Decodificador,Estimulo);
   Comparador22Numeros6Bit_Multiplexor U3 (RtaComparador22Numeros6Bit_Multiplexor,Estimulo);   


   Decodificador3a8 U4 (RtaDecodificador3a8,EstimuloDecodificador3a8);
   Multiplexor4a1 U5 (RtaMultiplexor4a1,Estimulo[5:4],Estimulo[3:0]);
   
   
   initial begin
      Estimulo = 6'b000000;
      EstimuloDecodificador3a8 = 3'b000;
   end

   initial begin
      repeat (62) begin
	 #1 Estimulo <= Estimulo + 1;
      end
   end

   initial begin
      repeat (8) begin
	 #1 EstimuloDecodificador3a8 = EstimuloDecodificador3a8 + 1;
      end
   end

   initial begin
      $dumpfile ("Laboratorio2_Lab.vcd");
      $dumpvars;
   end
   
endmodule // Laboratorio2_Lab

trunk/ld2ud/code/Laboratorio2_Lab.vcd
$date
	Wed Oct  7 16:43:15 2009
$end
$version
	Icarus Verilog
$end
$timescale
	1s
$end
$scope module Laboratorio2_Lab $end
$var wire 1 ! RtaComparador22Numeros6Bit_Compuertas $end
$var wire 1 " RtaComparador22Numeros6Bit_Decodificador $end
$var wire 1 # RtaComparador22Numeros6Bit_Multiplexor $end
$var wire 8 $ RtaDecodificador3a8[7:0] $end
$var wire 1 % RtaMultiplexor4a1 $end
$var reg 6 & Estimulo[5:0] $end
$var reg 3 ' EstimuloDecodificador3a8[2:0] $end
$scope module U1 $end
$var wire 6 ( Entrada[5:0] $end
$var wire 22 ) Nodo[21:0] $end
$var wire 1 ! Salida $end
$upscope $end
$scope module U2 $end
$var wire 8 * BusImpar[7:0] $end
$var wire 22 + BusOr[21:0] $end
$var wire 8 , BusPar[7:0] $end
$var wire 6 - Entrada[5:0] $end
$var wire 1 " Salida $end
$scope module U1 $end
$var wire 3 . Entrada[2:0] $end
$var wire 8 / Salida[7:0] $end
$upscope $end
$scope module U2 $end
$var wire 3 0 Entrada[2:0] $end
$var wire 8 1 Salida[7:0] $end
$upscope $end
$upscope $end
$scope module U3 $end
$var wire 4 2 BusMultiplexor[3:0] $end
$var wire 6 3 Entrada[5:0] $end
$var wire 1 # Salida $end
$scope module U1 $end
$var wire 4 4 BusOr[3:0] $end
$var wire 4 5 Entrada[3:0] $end
$var wire 1 # Salida $end
$var wire 2 6 Selector[1:0] $end
$upscope $end
$upscope $end
$scope module U4 $end
$var wire 3 7 Entrada[2:0] $end
$var wire 8 8 Salida[7:0] $end
$upscope $end
$scope module U5 $end
$var wire 4 9 BusOr[3:0] $end
$var wire 4 : Entrada[3:0] $end
$var wire 1 % Salida $end
$var wire 2 ; Selector[1:0] $end
$upscope $end
$upscope $end
$enddefinitions $end
#0
$dumpvars
b0 ;
b0 :
b0 9
b10000000 8
b0 7
b0 6
b0 5
b0 4
b0 3
b0 2
b10000000 1
b0 0
b10000000 /
b0 .
b0 -
b10000000 ,
b0 +
b10000000 *
b0 )
b0 (
b0 '
b0 &
0%
b10000000 $
0#
0"
0!
$end
#1
1!
1"
b1000000000000000000000 )
b1 +
b0x0x 2
b0x0x 5
b1000000 *
b1000000 1
b1 &
b1 (
b1 -
b1 0
b1 3
b1 :
b1000000 $
b1000000 8
b1 '
b1 7
#2
1"
x#
bx000 4
b100000000000000000000 )
b10 +
bx00x 2
bx00x 5
b100000 *
b100000 1
b10 &
b10 (
b10 -
b10 0
b10 3
b10 :
b100000 $
b100000 8
b10 '
b10 7
#3
b10000000000000000000 )
b100 +
bx0x 2
bx0x 5
b10000 *
b10000 1
b11 &
b11 (
b11 -
b11 0
b11 3
b11 :
b10000 $
b10000 8
b11 '
b11 7
#4
0!
0"
x#
bx000 4
b0 )
b0 +
bx0 2
bx0 5
b1000 *
b1000 1
b100 &
b100 (
b100 -
b100 0
b100 3
b100 :
b1000 $
b1000 8
b100 '
b100 7
#5
1!
1"
bx0xx 2
bx0xx 5
b1000000000000000000 )
b1000 +
b100 *
b100 1
b101 &
b101 (
b101 -
b101 0
b101 3
b101 :
b100 $
b100 8
b101 '
b101 7
#6
0!
0"
0#
b0 4
b0 )
b0 +
b0x0 2
b0x0 5
b10 *
b10 1
b110 &
b110 (
b110 -
b110 0
b110 3
b110 :
b10 $
b10 8
b110 '
b110 7
#7
b1 *
b1 1
b111 &
b111 (
b111 -
b111 0
b111 3
b111 :
b1 $
b1 8
b111 '
b111 7
#8
b0 2
b0 5
1%
b1000000 ,
b1000000 /
b1000 9
b10000000 *
b10000000 1
b1 .
b1000 &
b1000 (
b1000 -
b0 0
b1000 3
b1000 :
b10000000 $
b10000000 8
b0 '
b0 7
#9
b0x0 2
b0x0 5
b1000000 *
b1000000 1
b1001 &
b1001 (
b1001 -
b1 0
b1001 3
b1001 :
#10
1!
1"
b100000000000000000 )
b10000 +
b0x 2
b0x 5
b100000 *
b100000 1
b1010 &
b1010 (
b1010 -
b10 0
b1010 3
b1010 :
#11
0!
0"
b0 2
b0 5
b0 )
b0 +
b10000 *
b10000 1
b1011 &
b1011 (
b1011 -
b11 0
b1011 3
b1011 :
#12
1!
1"
b0x 2
b0x 5
b10000000000000000 )
b100000 +
b1000 *
b1000 1
b1100 &
b1100 (
b1100 -
b100 0
b1100 3
b1100 :
#13
b1000000000000000 )
b1000000 +
b100 *
b100 1
b1101 &
b1101 (
b1101 -
b101 0
b1101 3
b1101 :
#14
0!
0"
b0x0 2
b0x0 5
b0 )
b0 +
b10 *
b10 1
b1110 &
b1110 (
b1110 -
b110 0
b1110 3
b1110 :
#15
1!
1"
b0xx 2
b0xx 5
b100000000000000 )
b10000000 +
b1 *
b1 1
b1111 &
b1111 (
b1111 -
b111 0
b1111 3
b1111 :
#16
0!
0"
b0 2
b0 5
0%
b0 )
b0 +
b100000 ,
b100000 /
b0 9
b10000000 *
b10000000 1
b1 6
b1 ;
b10 .
b10000 &
b10000 (
b10000 -
b0 0
b10000 3
b0 :
#17
x#
b0x00 4
b0x0x 2
b0x0x 5
b1000000 *
b1000000 1
b10001 &
b10001 (
b10001 -
b1 0
b10001 3
b1 :
#18
0#
b0 4
bx00x 2
bx00x 5
b100000 *
b100000 1
b10010 &
b10010 (
b10010 -
b10 0
b10010 3
b10 :
#19
x#
b0x00 4
bx0x 2
bx0x 5
b10000 *
b10000 1
b10011 &
b10011 (
b10011 -
b11 0
b10011 3
b11 :
#20
1!
1"
x#
b10000000000000 )
b100000000 +
b0x00 4
1%
bx0 2
bx0 5
b100 9
b1000 *
b1000 1
b10100 &
b10100 (
b10100 -
b100 0
b10100 3
b100 :
#21
0#
b0 4
bx0xx 2
bx0xx 5
b1000000000000 )
b1000000000 +
b100 *
b100 1
b10101 &
b10101 (
b10101 -
b101 0
b10101 3
b101 :
#22
1"
b100000000000 )
b10000000000 +
b0x0 2
b0x0 5
b10 *
b10 1
b10110 &
b10110 (
b10110 -
b110 0
b10110 3
b110 :
#23
b10000000000 )
b100000000000 +
b1 *
b1 1
b10111 &
b10111 (
b10111 -
b111 0
b10111 3
b111 :
#24
0!
0"
b0 2
b0 5
0%
b0 )
b0 +
b10000 ,
b10000 /
b0 9
b10000000 *
b10000000 1
b11 .
b11000 &
b11000 (
b11000 -
b0 0
b11000 3
b1000 :
#25
1!
1"
b0x0 2
b0x0 5
b1000000000 )
b1000000000000 +
b1000000 *
b1000000 1
b11001 &
b11001 (
b11001 -
b1 0
b11001 3
b1001 :
#26
0!
0"
b0x 2
b0x 5
b0 )
b0 +
b100000 *
b100000 1
b11010 &
b11010 (
b11010 -
b10 0
b11010 3
b1010 :
#27
b0 2
b0 5
b10000 *
b10000 1
b11011 &
b11011 (
b11011 -
b11 0
b11011 3
b1011 :
#28
b0x 2
b0x 5
1%
b100 9
b1000 *
b1000 1
b11100 &
b11100 (
b11100 -
b100 0
b11100 3
b1100 :
#29
b100 *
b100 1
b11101 &
b11101 (
b11101 -
b101 0
b11101 3
b1101 :
#30
1!
1"
b100000000 )
b10000000000000 +
b0x0 2
b0x0 5
b10 *
b10 1
b11110 &
b11110 (
b11110 -
b110 0
b11110 3
b1110 :
#31
b0xx 2
b0xx 5
b10000000 )
b100000000000000 +
b1 *
b1 1
b11111 &
b11111 (
b11111 -
b111 0
b11111 3
b1111 :
#32
1!
1"
0#
b0 2
b0 5
b0 4
0%
b1000000 )
b1000000000000000 +
b1000 ,
b1000 /
b0 9
b10000000 *
b10000000 1
b10 6
b10 ;
b100 .
b100000 &
b100000 (
b100000 -
b0 0
b100000 3
b0 :
#33
b100000 )
b10000000000000000 +
b0x0x 2
b0x0x 5
b1000000 *
b1000000 1
b100001 &
b100001 (
b100001 -
b1 0
b100001 3
b1 :
#34
0!
0"
1%
b0 )
b0 +
bx00x 2
bx00x 5
b10 9
b100000 *
b100000 1
b100010 &
b100010 (
b100010 -
b10 0
b100010 3
b10 :
#35
1!
1"
b10000 )
b100000000000000000 +
bx0x 2
bx0x 5
b10000 *
b10000 1
b100011 &
b100011 (
b100011 -
b11 0
b100011 3
b11 :
#36
x#
b0x0 4
0!
0"
0%
b0 )
b0 +
bx0 2
bx0 5
b0 9
b1000 *
b1000 1
b100100 &
b100100 (
b100100 -
b100 0
b100100 3
b100 :
#37
bx0xx 2
bx0xx 5
b100 *
b100 1
b100101 &
b100101 (
b100101 -
b101 0
b100101 3
b101 :
#38
1%
b0x0 2
b0x0 5
b10 9
b10 *
b10 1
b100110 &
b100110 (
b100110 -
b110 0
b100110 3
b110 :
#39
b1 *
b1 1
b100111 &
b100111 (
b100111 -
b111 0
b100111 3
b111 :
#40
0#
b0 4
b0 +
b0 2
b0 5
0%
b100 ,
b100 /
b0 9
b10000000 *
b10000000 1
b101 .
b101000 &
b101000 (
b101000 -
b0 0
b101000 3
b1000 :
#41
x#
b0x0 4
b0x0 2
b0x0 5
b1000000 *
b1000000 1
b101001 &
b101001 (
b101001 -
b1 0
b101001 3
b1001 :
#42
0#
b0 4
b0x 2
b0x 5
1%
b10 9
b100000 *
b100000 1
b101010 &
b101010 (
b101010 -
b10 0
b101010 3
b1010 :
#43
b0 2
b0 5
b10000 *
b10000 1
b101011 &
b101011 (
b101011 -
b11 0
b101011 3
b1011 :
#44
b0x 2
b0x 5
0%
b0 9
b1000 *
b1000 1
b101100 &
b101100 (
b101100 -
b100 0
b101100 3
b1100 :
#45
b100 *
b100 1
b101101 &
b101101 (
b101101 -
b101 0
b101101 3
b1101 :
#46
x#
b0x0 4
b0x0 2
b0x0 5
1%
b10 9
b10 *
b10 1
b101110 &
b101110 (
b101110 -
b110 0
b101110 3
b1110 :
#47
b0xx 2
b0xx 5
b1 *
b1 1
b101111 &
b101111 (
b101111 -
b111 0
b101111 3
b1111 :
#48
0#
b0 2
b0 5
0%
b0 4
b10 ,
b10 /
b0 9
b10000000 *
b10000000 1
b11 6
b11 ;
b110 .
b110000 &
b110000 (
b110000 -
b0 0
b110000 3
b0 :
#49
x#
b0x 4
b0x0x 2
b0x0x 5
1%
b1000000 *
b1000000 1
b1 9
b110001 &
b110001 (
b110001 -
b1 0
b110001 3
b1 :
#50
1!
1"
b1000 )
b1000000000000000000 +
bx00x 2
bx00x 5
0%
b100000 *
b100000 1
b0 9
b110010 &
b110010 (
b110010 -
b10 0
b110010 3
b10 :
#51
b100 )
b10000000000000000000 +
bx0x 2
bx0x 5
1%
b10000 *
b10000 1
b1 9
b110011 &
b110011 (
b110011 -
b11 0
b110011 3
b11 :
#52
1!
1"
0#
b0 4
b10 )
b100000000000000000000 +
bx0 2
bx0 5
0%
b1000 *
b1000 1
b0 9
b110100 &
b110100 (
b110100 -
b100 0
b110100 3
b100 :
#53
x#
b0x 4
bx0xx 2
bx0xx 5
b1 )
b1000000000000000000000 +
1%
b100 *
b100 1
b1 9
b110101 &
b110101 (
b110101 -
b101 0
b110101 3
b101 :
#54
0!
0"
0#
b0 4
b0 )
b0 +
b0x0 2
b0x0 5
0%
b10 *
b10 1
b0 9
b110110 &
b110110 (
b110110 -
b110 0
b110110 3
b110 :
#55
1%
b1 *
b1 1
b1 9
b110111 &
b110111 (
b110111 -
b111 0
b110111 3
b111 :
#56
b0 2
b0 5
0%
b1 ,
b1 /
b10000000 *
b10000000 1
b0 9
b111 .
b111000 &
b111000 (
b111000 -
b0 0
b111000 3
b1000 :
#57
b0x0 2
b0x0 5
1%
b1000000 *
b1000000 1
b1 9
b111001 &
b111001 (
b111001 -
b1 0
b111001 3
b1001 :
#58
x#
b0x 4
b0x 2
b0x 5
0%
b100000 *
b100000 1
b0 9
b111010 &
b111010 (
b111010 -
b10 0
b111010 3
b1010 :
#59
0#
b0 4
b0 2
b0 5
1%
b10000 *
b10000 1
b1 9
b111011 &
b111011 (
b111011 -
b11 0
b111011 3
b1011 :
#60
x#
b0x 4
b0x 2
b0x 5
0%
b1000 *
b1000 1
b0 9
b111100 &
b111100 (
b111100 -
b100 0
b111100 3
b1100 :
#61
1%
b100 *
b100 1
b1 9
b111101 &
b111101 (
b111101 -
b101 0
b111101 3
b1101 :
#62
0#
b0 4
b0x0 2
b0x0 5
0%
b10 *
b10 1
b0 9
b111110 &
b111110 (
b111110 -
b110 0
b111110 3
b1110 :
