trunk/ld2ud/code/DesplazaDerecha2Bits.v
module DesplazaDerecha2Bits (/*AUTOARG*/
   // Outputs
   Salida,
   // Inputs
   Entrada
   ) ;
   output [7:0] Salida;
   input  [7:0] Entrada;
//#######################parece que no funciona :(
   assign Salida = Entrada >> 2;
endmodule // DesplazaDerecha2Bits

ld2ud/code/RotaIzquierda2Bits.v
//http://ld2ud.altaimpedancia.org - más información en el pié de página
//Electrónica con Software Libre, Free Hardware Design y Open Source Hardware

module RotaIzquierda2Bits (/*AUTOARG*/
   // Outputs
   Salida,
   // Inputs
   Entrada
   ) ;
   output [7:0] Salida;
   input  [7:0] Entrada;

   assign Salida = {Entrada[1:0],Entrada[7:2]};
   
endmodule // RotaIzquierda2Bits


/* Para escribir, compilar y visualizar se usó Software Libre:
  * Debian GNU/Linux como sistema operativo
  * GNU Emacs 22.2.1 con verilog-mode 404 para escribir el codigo Verilog (.v)
  * Icarus Verilog version 0.8.6 para compilar y simular
  * GTKWave Analyzer v3.1.10 para visualizar el resultado de las simulaciones (.vcd)
 * Autor: Fredy Pulido López (digitalfredy)
 * Copyright: http://www.fsf.org/licensing/licenses/gpl.html
*/

trunk/ld2ud/code/XorUsandoNand_Estructural.v
//Electrónica con Software Libre, Free Hardware Design y Open Source Hardware
//http://ld2ud.altaimpedancia.org - más información en el pié de página

module XorUsandoNand_Estructural (/*AUTOARG*/
   // Outputs
   Salida,
   // Inputs
   Entrada
   ) ;
   output Salida;
   input  [1:0] Entrada;
   wire   CableA, CableB, CableC, CableD;

   nand InstalnciaNand1 (CableA,Entrada[1],Entrada[1]);
   nand InstalnciaNand2 (CableB,Entrada[0],Entrada[0]);
   nand InstalnciaNand3 (CableC,CableA,Entrada[0]);
   nand InstalnciaNand4 (CableD,CableB,Entrada[1]);
   nand InstalnciaNand5 (Salida,CableC,CableD);
   
   
endmodule // XorUsandoNand_Estructural

//referencia: http://hyperphysics.phy-astr.gsu.edu/HBASE/Electronic/xor.html

trunk/ld2ud/code/XorOperadorCondicional_Funcional.v
//Electrónica con Software Libre, Free Hardware Design y Open Source Hardware
//http://ld2ud.altaimpedancia.org - más información en el pié de página

module XorOperadorCondicional_Funcional (/*AUTOARG*/
   // Outputs
   Salida,
   // Inputs
   Entrada
   ) ;
   output Salida;
   input  [1:0] Entrada;
   assign Salida = (Entrada=='b01) ? 'b1 :
		   (Entrada=='b10) ? 'b1 :
		    'b0;
endmodule // XorOperadorCondicional_Funcional

trunk/ld2ud/code/XorOperadorBitABit_Funcional.v
//Electrónica con Software Libre, Free Hardware Design y Open Source Hardware
//http://ld2ud.altaimpedancia.org - más información en el pié de página

module XorOperadorBitABit_Funcional (/*AUTOARG*/
   // El orden en que se ponen aqui es el mismo en el que las recibe
   // Outputs
   Salida,
   // Inputs
   Entrada
   );
   input  [1:0] Entrada;
   output Salida;
   assign Salida = Entrada[1]^Entrada[0];
endmodule // XorOperadorBitABit_Funcional

trunk/ld2ud/code/AndUsandoNand_Estructural.v
module AndUsandoNand_Estructural (/*AUTOARG*/
   // Outputs
   Salida,
   // Inputs
   Entrada
   ) ;
   output Salida;
   input  [1:0] Entrada;
   wire   Cable;

   nand InstanciaNand1 (Cable,Entrada[1],Entrada[0]);
   nand InstanciaNand2 (Salida,Cable,Cable);
   
endmodule // AndUsandoNand_Estructural

ld2ud/code/AndOperadorCondicional_Funcional.v
//Electrónica con Software Libre, Free Hardware Design y Open Source Hardware
//http://ld2ud.altaimpedancia.org - más información en el pié de página

module AndOperadorCondicional_Funcional (/*AUTOARG*/
   // Outputs
   Salida,
   // Inputs
   Entrada
   ) ;
   output Salida;
   input  [1:0] Entrada;
   
   assign Salida = (Entrada=='b11) ? 'b1 : 'b0;
endmodule // AndOperadorCondicional_Funcional

ld2ud/code/AndOperadorBitABit_Funcional.v
module AndOperadorBitABit_Funcional (/*AUTOARG*/
   // El orden en que se ponen aqui es el mismo en el que las recibe
   // Outputs
   Salida,
   // Inputs
   Entrada
   );
   input  [1:0] Entrada;
   output Salida;
   assign Salida = Entrada[1]&Entrada[0];
endmodule // AndOperadorBitABit_Funcional

ld2ud/code/Laboratorio1_Lab.v
//Electrónica con Software Libre, Free Hardware Design y Open Source Hardware
//http://ld2ud.altaimpedancia.org - más información en el pié de página

module Laboratorio1 (/*AUTOARG*/) ;
//Registros y alambres para punto 1 en Verilog de doc/Taller1.pdf
   reg   [1:0] EstimuloCompuertas;
   wire        RtaAndOperadorBitABit_Funcional,RtaAndOperadorCondicional_Funcional,RtaAndUsandoNand_Estructural; 
   wire        RtaXorOperadorBitABit_Funcional,RtaXorOperadorCondicional_Funcional,RtaXorUsandoNand_Estructural;
//Registros y alambres para punto 2 en Verilog de doc/Taller1.pdf
   reg   [7:0] Palabra;
   wire   [7:0] RtaRotaIzquierda2Bits,RtaDesplazaDerecha2Bits;
//Instanciando y conectando dispositivos para punto 1
   AndOperadorBitABit_Funcional InstanciaAndOperadorBitABit_Funcional(RtaAndOperadorBitABit_Funcional,EstimuloCompuertas[1:0]);   
   AndOperadorCondicional_Funcional InstanciaAndOperadorCondicional_Funcional(RtaAndOperadorCondicional_Funcional,EstimuloCompuertas[1:0]);
   AndUsandoNand_Estructural InstanciaAndUsandoNand_Estructural (RtaAndUsandoNand_Estructural,EstimuloCompuertas);   
   XorOperadorBitABit_Funcional InstanciaXorOperadorBitABit_Funcional(RtaXorOperadorBitABit_Funcional,EstimuloCompuertas[1:0]);
   XorOperadorCondicional_Funcional InstanciaXorOperadorCondicional_Funcional(RtaXorOperadorCondicional_Funcional,EstimuloCompuertas[1:0]);   
   XorUsandoNand_Estructural InstanciaXorUsandoNand_Estructural (RtaXorUsandoNand_Estructural,EstimuloCompuertas);
//Simulación punto1
   initial begin
      EstimuloCompuertas = 'b00;
   end

   initial begin
      repeat (4) begin
	 #1 EstimuloCompuertas <= EstimuloCompuertas+1;
      end
   end

//Instanciando y conectando dispositivos para punto 2
   RotaIzquierda2Bits InstanciaRotaIzquierda2Bits(RtaRotaIzquierda2Bits,Palabra);
   DesplazaDerecha2Bits InstanciaDesplazaDerecha2Bits(RtaDesplazaDerecha2Bits,Palabra);
//Simulación punto1
   initial begin
      Palabra = 'b0000_0000;
   end
   
   initial begin
      repeat (8) begin
	 #1 Palabra <= Palabra+1;
      end
      
   end
   

//Archivo con los resultados de la simulación puntos 1 y 2
   initial begin
      $dumpfile ("Laboratorio1_Lab.vcd");
      $dumpvars;
   end
endmodule // Laboratorio1

trunk/ld2ud/code/Laboratorio1_Lab.vcd
$date
	Thu Sep 17 12:59:27 2009
$end
$version
	Icarus Verilog
$end
$timescale
	1s
$end
$scope module Laboratorio1 $end
$var wire 1 ! RtaAndOperadorBitABit_Funcional $end
$var wire 1 " RtaAndOperadorCondicional_Funcional $end
$var wire 1 # RtaAndUsandoNand_Estructural $end
$var wire 8 $ RtaDesplazaDerecha2Bits[7:0] $end
$var wire 8 % RtaRotaIzquierda2Bits[7:0] $end
$var wire 1 & RtaXorOperadorBitABit_Funcional $end
$var wire 1 ' RtaXorOperadorCondicional_Funcional $end
$var wire 1 ( RtaXorUsandoNand_Estructural $end
$var reg 2 ) EstimuloCompuertas[1:0] $end
$var reg 8 * Palabra[7:0] $end
$scope module InstanciaAndOperadorBitABit_Funcional $end
$var wire 2 + Entrada[1:0] $end
$var wire 1 ! Salida $end
$upscope $end
$scope module InstanciaAndOperadorCondicional_Funcional $end
$var wire 2 , Entrada[1:0] $end
$var wire 1 " Salida $end
$upscope $end
$scope module InstanciaAndUsandoNand_Estructural $end
$var wire 1 - Cable $end
$var wire 2 . Entrada[1:0] $end
$var wire 1 # Salida $end
$upscope $end
$scope module InstanciaXorOperadorBitABit_Funcional $end
$var wire 2 / Entrada[1:0] $end
$var wire 1 & Salida $end
$upscope $end
$scope module InstanciaXorOperadorCondicional_Funcional $end
$var wire 2 0 Entrada[1:0] $end
$var wire 1 ' Salida $end
$upscope $end
$scope module InstanciaXorUsandoNand_Estructural $end
$var wire 1 1 CableA $end
$var wire 1 2 CableB $end
$var wire 1 3 CableC $end
$var wire 1 4 CableD $end
$var wire 2 5 Entrada[1:0] $end
$var wire 1 ( Salida $end
$upscope $end
$scope module InstanciaRotaIzquierda2Bits $end
$var wire 8 6 Entrada[7:0] $end
$var wire 8 7 Salida[7:0] $end
$upscope $end
$scope module InstanciaDesplazaDerecha2Bits $end
$var wire 8 8 Entrada[7:0] $end
$var wire 8 9 Salida[7:0] $end
$upscope $end
$upscope $end
$enddefinitions $end
#0
$dumpvars
b0 9
b0 8
b0 7
b0 6
b0 5
14
13
12
11
b0 0
b0 /
b0 .
1-
b0 ,
b0 +
b0 *
b0 )
0(
0'
0&
b0 %
b0 $
0#
0"
0!
$end
#1
1'
1(
1&
02
03
b1000000 %
b1 *
b1 6
b1000000 7
b1 8
b1 )
b1 +
b1 ,
b1 .
b1 /
b1 0
b1 5
#2
1'
04
1(
01
1&
12
13
b10000000 %
b10 *
b10 6
b10000000 7
b10 8
b10 )
b10 +
b10 ,
b10 .
b10 /
b10 0
b10 5
#3
0'
0(
1#
14
1!
1"
0-
0&
02
b11000000 %
b11 *
b11 6
b11000000 7
b11 8
b11 )
b11 +
b11 ,
b11 .
b11 /
b11 0
b11 5
#4
0#
11
0!
0"
1-
0&
12
b1 $
b1 9
b1 %
b100 *
b100 6
b1 7
b100 8
b0 )
b0 +
b0 ,
b0 .
b0 /
b0 0
b0 5
#5
b1000001 %
b101 *
b101 6
b1000001 7
b101 8
#6
b10000001 %
b110 *
b110 6
b10000001 7
b110 8
#7
b11000001 %
b111 *
b111 6
b11000001 7
b111 8
#8
b10 $
b10 9
b10 %
b1000 *
b1000 6
b10 7
b1000 8
