trunk/ld2ud/code/ciscud/IgualCero.v
module IgualCero (/*AUTOARG*/
   // Outputs
   Salida,
   // Inputs
   Entrada
   ) ;
   output Salida;
   input  [15:0] Entrada;

   assign Salida = (Entrada == 16'h0) ? 1'b1 : 1'b0;
endmodule // IgualCero

ld2ud/code/ciscud/IgualCero_Lab.v
module IgualCero_Lab (/*AUTOARG*/
   // Outputs
   Tupla
   ) ;
   output reg [15:0] Tupla;

   wire   Respuesta;

   IgualCero IgualCero (Respuesta,Tupla);

   //Simulación:
   initial begin
      repeat (8) begin
	 #1 Tupla <= Tupla+1;
      end
   end

   initial begin
      #0 Tupla <= 16'h0;
   end

   initial begin
      #9 Tupla <= 16'h0;
   end

   initial begin
      #12 Tupla <= 16'h7;
   end
   
   initial begin
      $dumpfile ("IgualCero_Lab.vcd");
      $dumpvars;

   end
   
   
endmodule // IgualCero_Lab

trunk/ld2ud/code/ciscud/IgualCero_Lab.vcd
$date
	Tue Dec  1 21:13:56 2009
$end
$version
	Icarus Verilog
$end
$timescale
	1s
$end
$scope module IgualCero_Lab $end
$var wire 1 ! Respuesta $end
$var reg 16 " Tupla[15:0] $end
$scope module IgualCero $end
$var wire 16 # Entrada[15:0] $end
$var wire 1 ! Salida $end
$upscope $end
$upscope $end
$enddefinitions $end
#0
$dumpvars
b0 #
b0 "
1!
$end
#1
0!
b1 "
b1 #
#2
b10 "
b10 #
#3
b11 "
b11 #
#4
b100 "
b100 #
#5
b101 "
b101 #
#6
b110 "
b110 #
#7
b111 "
b111 #
#8
b1000 "
b1000 #
#9
1!
b0 "
b0 #
#12
0!
b111 "
b111 #
