trunk/ld2ud/code/ciscud/Memoria16X16Bits.v
module Memoria16X16Bits (/*AUTOARG*/
   // Outputs
   Salida,
   // Inputs
   Entrada, Reloj, HabilitarSalida, HabilitarEscritura, Direccion
   ) ;
   output reg [15:0] Salida;
   input  [15:0] Entrada;
   input  Reloj, HabilitarSalida, HabilitarEscritura;
   input  [15:0] Direccion;

   reg   [15:0] Memoria [15:0];

   //LoadInmediato del numero 23 en registro 0

   always @ (posedge Reloj) begin
      Memoria[16'h0] = 16'h4000;
      Memoria[16'h1] = 16'h0017;

     if (HabilitarEscritura)  begin
	Memoria[Direccion] <= Entrada;
	Salida <= 16'hz;
     end
     else if (HabilitarSalida) begin
	Salida <= Memoria[Direccion];
//	Entrada <= 16'hz;
     end
      else  begin
	 Salida <= 16'hz;
      end
      
   end
   
endmodule // Memoria16X16Bits

ld2ud/code/ciscud/Memoria16X16Bits_Lab.v
module Memoria16X16Bits_Lab (/*AUTOARG*/
   // Outputs
   Dato2M, Direccion, Leer, Escribir, Reloj
   ) ;
   output reg [15:0] Dato2M;
   output reg [15:0] Direccion;
   output reg Leer, Escribir, Reloj;

   wire   [15:0] Rta;
   Memoria16X16Bits Mem(Rta,Dato2M,Reloj,Leer,Escribir,Direccion);

   initial begin
      Direccion <= 16'h0;
      Reloj <= 1'b0;
      Leer <= 1'bz;
      Escribir <= 1'bz;
   end

   initial begin
      repeat (8) begin
	 #1 Reloj <= ~Reloj;
      end
      
   end
   
   initial begin
      #1 Leer <= 1'b1;
      #1 Leer <= 1'b0;
   end
   
//      #1 Escribir <=1'b1;
//      #1 Direccion <= 16'h7;
   initial begin
      $dumpfile("Memoria16X16Bits_Lab.vcd");
      $dumpvars;
   end
   
endmodule // Memoria16X16Bits_Lab

trunk/ld2ud/code/ciscud/Memoria16X16Bits_Lab.vcd
$date
	Wed Dec  9 02:01:49 2009
$end
$version
	Icarus Verilog
$end
$timescale
	1s
$end
$scope module Memoria16X16Bits_Lab $end
$var wire 16 ! Rta[15:0] $end
$var reg 16 " Dato2M[15:0] $end
$var reg 16 # Direccion[15:0] $end
$var reg 1 $ Escribir $end
$var reg 1 % Leer $end
$var reg 1 & Reloj $end
$scope module Mem $end
$var wire 16 ' Direccion[15:0] $end
$var wire 16 ( Entrada[15:0] $end
$var wire 1 $ HabilitarEscritura $end
$var wire 1 % HabilitarSalida $end
$var wire 1 & Reloj $end
$var reg 16 ) Salida[15:0] $end
$upscope $end
$upscope $end
$enddefinitions $end
#0
$dumpvars
bx )
bx (
b0 '
0&
z%
z$
b0 #
bx "
bx !
$end
#1
b100000000000000 !
b100000000000000 )
1%
1&
#2
0%
0&
#3
bz !
bz )
1&
#4
0&
#5
1&
#6
0&
#7
1&
#8
0&
