ld2ud/code/ciscud/Registro16Bits.v
module Registro16Bit (/*AUTOARG*/
   // Outputs
   Salida,
   // Inputs
   Entrada, Reloj, Reiniciar, Habilitar
   ) ;
   output reg [15:0] Salida;
   input  [15:0] Entrada;
   input  Reloj, Reiniciar, Habilitar;

   always @ (posedge Reloj, posedge Reiniciar)
      if (Reiniciar)
	Salida <= 16'h0;
      else if (Habilitar)
	Salida <= Entrada;

endmodule // Registro16Bit

trunk/ld2ud/code/ciscud/Registro16Bits_Lab.v
module Registro16Bits_Lab (/*AUTOARG*/
   // Outputs
   Tupla, Reloj, Reiniciar, Habilitar
   ) ;
   output reg [15:0] Tupla;
   output reg Reloj, Reiniciar, Habilitar;

   wire   [15:0] RtaRegistro;
   
   Registro16Bit RegistroPrueba (RtaRegistro, Tupla, Reloj, Reiniciar, Habilitar);

   //Simulación:
   initial begin
      Tupla     = 16'h0;
      Reloj     = 1'b0;
      Reiniciar = 1'b0;
      Habilitar = 1'b0;
   end

   initial begin
      repeat (16) begin
	 #1 Reloj <= ~Reloj;
      end
   end

   initial begin
      repeat (16) begin
	 #1 Tupla <= Tupla+1;
      end
   end
   
   initial begin
      #8 Habilitar = 1'b1;
   end

   initial begin
      $dumpfile ("Registro16Bits_Lab.vcd");
      $dumpvars;
   end  
   
endmodule // Registro16Bits_Lab

trunk/ld2ud/code/ciscud/Registro16Bits_Lab.vcd
$date
	Fri Nov 20 13:32:02 2009
$end
$version
	Icarus Verilog
$end
$timescale
	1s
$end
$scope module Registro16Bits_Lab $end
$var wire 16 ! RtaRegistro[15:0] $end
$var reg 1 " Habilitar $end
$var reg 1 # Reiniciar $end
$var reg 1 $ Reloj $end
$var reg 16 % Tupla[15:0] $end
$scope module RegistroPrueba $end
$var wire 16 & Entrada[15:0] $end
$var wire 1 " Habilitar $end
$var wire 1 # Reiniciar $end
$var wire 1 $ Reloj $end
$var reg 16 ' Salida[15:0] $end
$upscope $end
$upscope $end
$enddefinitions $end
#0
$dumpvars
bx '
b0 &
b0 %
0$
0#
0"
bx !
$end
#1
b1 %
b1 &
1$
#2
b10 %
b10 &
0$
#3
b11 %
b11 &
1$
#4
b100 %
b100 &
0$
#5
b101 %
b101 &
1$
#6
b110 %
b110 &
0$
#7
b111 %
b111 &
1$
#8
b1000 %
b1000 &
0$
1"
#9
b1001 !
b1001 '
b1001 %
b1001 &
1$
#10
b1010 %
b1010 &
0$
#11
b1011 !
b1011 '
b1011 %
b1011 &
1$
#12
b1100 %
b1100 &
0$
#13
b1101 !
b1101 '
b1101 %
b1101 &
1$
#14
b1110 %
b1110 &
0$
#15
b1111 !
b1111 '
b1111 %
b1111 &
1$
#16
b10000 %
b10000 &
0$
