trunk/ld2ud/code/ciscud/ciscud/Registro4Bits.v
module Registro4Bit (/*AUTOARG*/
   // Outputs
   Salida,
   // Inputs
   Entrada, Reloj, Reiniciar, Habilitar
   ) ;
   output reg [3:0] Salida;
   input  [3:0] Entrada;
   input  Reloj, Reiniciar, Habilitar;

   always @ (posedge Reloj, posedge Reiniciar)
      if (Reiniciar)
	Salida <= 4'b0000;
      else if (Habilitar)
	Salida <= Entrada;

endmodule // Registro4Bit

ld2ud/code/ciscud/Registro4Bits_Lab.v
module Registro14Bits_Lab (/*AUTOARG*/
   // Outputs
   Tupla, Reloj, Reiniciar, Habilitar
   ) ;
   output reg [3:0] Tupla;
   output reg Reloj, Reiniciar, Habilitar;

   wire   [3:0] RtaRegistro;
   
   Registro4Bit RegistroPrueba (RtaRegistro, Tupla, Reloj, Reiniciar, Habilitar);

   //Simulación:
   initial begin
      Tupla     = 4'b0000;
      Reloj     = 1'b0;
      Reiniciar = 1'b0;
      Habilitar = 1'b0;
   end

   initial begin
      repeat (8) begin
	 #1 Reloj <= ~Reloj;
      end
   end

   initial begin
      repeat (8) begin
	 #1 Tupla <= Tupla+1;
      end
   end
   
   initial begin
      #3 Habilitar = 1'b1;
   end

   initial begin
      $dumpfile ("Registro4Bits_Lab.vcd");
      $dumpvars;
   end  
   
endmodule // Registro4Bits_Lab

trunk/ld2ud/code/ciscud/Registro4Bits_Lab.vcd
$date
	Mon Nov 23 00:24:17 2009
$end
$version
	Icarus Verilog
$end
$timescale
	1s
$end
$scope module Registro14Bits_Lab $end
$var wire 4 ! RtaRegistro[3:0] $end
$var reg 1 " Habilitar $end
$var reg 1 # Reiniciar $end
$var reg 1 $ Reloj $end
$var reg 4 % Tupla[3:0] $end
$scope module RegistroPrueba $end
$var wire 4 & Entrada[3:0] $end
$var wire 1 " Habilitar $end
$var wire 1 # Reiniciar $end
$var wire 1 $ Reloj $end
$var reg 4 ' Salida[3:0] $end
$upscope $end
$upscope $end
$enddefinitions $end
#0
$dumpvars
bx '
b0 &
b0 %
0$
0#
0"
bx !
$end
#1
b1 %
b1 &
1$
#2
b10 %
b10 &
0$
#3
b11 !
b11 '
b11 %
b11 &
1$
1"
#4
b100 %
b100 &
0$
#5
b101 !
b101 '
b101 %
b101 &
1$
#6
b110 %
b110 &
0$
#7
b111 !
b111 '
b111 %
b111 &
1$
#8
b1000 %
b1000 &
0$
