ld2ud/code/ciscud/UnidadDeControl.v
module UnidadDeControl (/*AUTOARG*/
   // Outputs
   Control, SelectDR, LoadDR, SelectAR, LoadAR, SelectPC, LoadPC,
   LoadIR, LoadCR, WriteSelect, WriteEnable, WriteAddress,
   ReadAddressA, ReadAddressB, Fun,
   // Inputs
   Instruccion, Reloj, Reiniciar
   ) ;
   
   output reg [5:0] Control;
/* -----\/----- EXCLUDED -----\/-----
   
   output reg 	    LoadS;
   output reg [1:0] SelectS;
   output reg 	    NegS;
 -----/\----- EXCLUDED -----/\----- */
   
   output reg 	    SelectDR, LoadDR;
   output reg 	    SelectAR, LoadAR;
   
   output reg [1:0] SelectPC;
   output reg 	    LoadPC;
   
   output reg 	    LoadIR, LoadCR;
   
   output reg 	    WriteSelect, WriteEnable;
   output reg [2:0] WriteAddress, ReadAddressA, ReadAddressB;
   
   output reg [3:0] Fun;
   


   input  [15:0] Instruccion;
//   input  StatusFlag;
   input  Reloj, Reiniciar;
   

   localparam [6:0]
     SF1   = 6'd000000,
     SF2   = 6'b000001,
     SF3   = 6'b000010,
     
     S01   = 6'b000011,
     S02   = 6'b000100,
     S031  = 6'b000101,
     S032  = 6'b000110,
     S04   = 6'b000111,
     
     S1R01 = 6'b001000,
     S1R11 = 6'b001001,
     S1R12 = 6'b001010,
     S1W10 = 6'b001011,
     S1W11 = 6'b001100,
     S1R21 = 6'b001101,
     S1R22 = 6'b001110,
     S1R23 = 6'b001111,
     S1W20 = 6'b010000,
     S1W21 = 6'b010001,
     S1W22 = 6'b010010,
     S1R31 = 6'b010011,
     S1R32 = 6'b010100,
     S1R33 = 6'b010101,
     S1W30 = 6'b010110,
     S1W31 = 6'b010111,
     S1W32 = 6'b011000,
     
     S21   = 6'b011001,
     S22   = 6'b011010,
     S23   = 6'b011011,
     S24   = 6'b011100,
     S25   = 6'b011101,
     S26   = 6'b011110,
     S27   = 6'b011111,
     S28   = 6'b100000;

   reg [10:0] LoadSelect;  //habilitadores en una palabra (excepto los de Satus)
                              //(referencia en hoja de calculo UnidadDeControl_Operaciones.ods)
   always @* begin
      LoadSelect <= {SelectDR,LoadDR,
			SelectAR,LoadAR,
			SelectPC,LoadPC,
			LoadIR,LoadCR,
			WriteSelect,WriteEnable};
   end
/* -----\/----- EXCLUDED -----\/-----
   
   reg [3:0]  ControlStatus;
   always @* begin
      ControlStatus <= {LoadS,SelectS,NegS};
   end
 -----/\----- EXCLUDED -----/\----- */
   
   
   reg   [6:0] EstadoPresente, EstadoFuturo;

   always @ (posedge Reloj, posedge Reiniciar) //Registro de estado
     if (Reiniciar) begin // es el mismo reset del camino de datos que reinicializa
	                  // todos los registros y garantiza CR <= (--) && PC<=0
	EstadoFuturo <= SF1;
     end 
     else
       EstadoPresente <= EstadoFuturo;

      
   always @* //EntradaCombinacional
     case (EstadoPresente)
       SF1: begin
	  EstadoFuturo <= SF2;
	  Control      <= 6'b100_100;
	  LoadSelect   <= 11'bzzzz_zzz_z1zz;
	  WriteAddress <= 3'bzzz;
	  ReadAddressA <= 3'bzzz;
	  ReadAddressB <= 3'bzzz;
	  Fun          <= 4'bzzzz;
       end
       SF2: begin
	  EstadoFuturo <= SF3;
	  Control      <= 6'bzzz_zzz;
	  LoadSelect   <= 11'bzzzz_111_1zzz;
	  WriteAddress <= 3'bzzz;
	  ReadAddressA <= 3'bzzz;
	  ReadAddressB <= 3'bzzz;
	  Fun          <= 4'bzzzz;
       end
       SF3: begin
	  if (Instruccion[15])  begin
	     if (Instruccion[14]) begin
		EstadoFuturo <= SF1;
	     end
	     else begin
		if (Instruccion[13]) begin
		   if (Instruccion[12]) begin
		      EstadoFuturo <= S27;
		   end
		   else begin
		      EstadoFuturo <= S23;
		   end
		end
		else begin
		   if (Instruccion[12]) begin
//pendiente, es aqui cuando se revisa status		      
		   end
		   else begin
		      EstadoFuturo <= S21;
		   end
		end
	     end
	  end
	  else begin
	     if (Instruccion[14]) begin
		if (Instruccion[10]) begin
		   if (Instruccion[9]) begin
		      if (Instruccion[11]) begin
			 EstadoFuturo <= S1W30;
		      end
		      else begin
			 EstadoFuturo <= S1R31;
		      end
		   end
		   else begin
		      if (Instruccion[11]) begin
			 EstadoFuturo <= S1W20;
		      end
		      else begin
			 EstadoFuturo <= S1R21;
		      end
		   end
		end
		else begin
		   if (Instruccion[9]) begin
		      if (Instruccion[11]) begin
			 EstadoFuturo <= S1W10;
		      end
		      else begin
			 EstadoFuturo <= S1R11;
		      end
		   end
		   else begin
		      EstadoFuturo <= S1R01;
		   end
		end
	     end
	     else begin
		if (Instruccion[12]) begin
		   if (Instruccion[11]) begin
		      EstadoFuturo <= S04;
		   end
		   else begin
		      //estado desconocido pendiente
		   end
		end
		else begin
		   if (Instruccion[11]) begin
		      EstadoFuturo <= S02;
		   end
		   else begin
		      EstadoFuturo <= S01;
		   end
		end
	     end
	  end
       end
       S01: begin
	  EstadoFuturo <= SF1;
	  Control      <= 6'bzzz_zzz;
	  LoadSelect   <= 11'bzzzz_zzz_zz01;
	  WriteAddress <= Instruccion[8:6];
	  ReadAddressA <= Instruccion[5:3];
	  ReadAddressB <= Instruccion[2:0];
	  Fun          <= Instruccion[12:9];
       end
       S02: begin
	  EstadoFuturo <= SF1;
	  Control      <= 6'bzzz_zzz;
	  LoadSelect   <= 11'bzzzz_zzz_zz01;
	  WriteAddress <= Instruccion[8:6];
	  ReadAddressA <= Instruccion[5:3];
	  ReadAddressB <= Instruccion[2:0];
	  Fun          <= Instruccion[12:9];
       end
/* -----\/----- EXCLUDED -----\/-----
       S031: begin
	  EstadoFuturo <= SF1;
	  Control      <= 6'bzzz_zzz;
	  LoadSelect   <= 11'b;
	  WriteAddress <= 3'bzzz;
	  ReadAddressA <= 3'bzzz;
	  ReadAddressB <= 3'bzzz;
	  Fun          <= 4'bzzzz;
       end
       S032: begin
	  EstadoFuturo <= SF1;
	  Control      <= 6'bzzz_zzz;
	  LoadSelect   <= 11'b;
	  WriteAddress <= 3'bzzz;
	  ReadAddressA <= 3'bzzz;
	  ReadAddressB <= 3'bzzz;
	  Fun          <= 4'bzzzz;
       end
 -----/\----- EXCLUDED -----/\----- */
       S04: begin
	  EstadoFuturo <= SF1;
	  Control      <= 6'bzzz_zzz;
	  LoadSelect   <= 11'bzzzz_zzz_zz01;
	  WriteAddress <= Instruccion[8:6];
	  ReadAddressA <= Instruccion[5:3];
	  ReadAddressB <= 3'bzzz;
	  Fun          <= Instruccion[12:9];
       end
       S1R01: begin
	  EstadoFuturo <= SF1;
	  Control      <= 6'bzzz_zzz;
	  LoadSelect   <= 11'bzzzz_111_zz11;
	  WriteAddress <= Instruccion[8:6];
	  ReadAddressA <= 3'bzzz;
	  ReadAddressB <= 3'bzzz;
	  Fun          <= 4'bzzzz;
       end
       S1R11: begin
	  EstadoFuturo <= S1R12;
	  Control      <= 6'b100010;
	  LoadSelect   <= 11'bzz01_zzz_z1zz;
	  WriteAddress <= 3'bzzz;
	  ReadAddressA <= 3'bzzz;
	  ReadAddressB <= 3'bzzz;
	  Fun          <= 4'bzzzz;
       end
       S1R12: begin
	  EstadoFuturo <= SF1;
	  Control      <= 6'bzzz_zzz;
	  LoadSelect   <= 11'bzzzz_111_zz11;
	  WriteAddress <= Instruccion[8:6];
	  ReadAddressA <= 3'bzzz;
	  ReadAddressB <= 3'bzzz;
	  Fun          <= 4'bzzzz;
       end
       S1W10: begin
	  EstadoFuturo <= S1W11;
	  Control      <= 6'b001011;
	  LoadSelect   <= 11'b1101_zzz_z1z0;
	  WriteAddress <= 3'bzzz;
	  ReadAddressA <= Instruccion[5:3];
	  ReadAddressB <= 3'bzzz;
	  Fun          <= 4'b1000;
       end
       S1W11: begin
	  EstadoFuturo <= SF1;
	  Control      <= 6'b001010;
	  LoadSelect   <= 11'bzzzz_111_z1zz;
	  WriteAddress <= 3'bzzz;
	  ReadAddressA <= 3'bzzz;
	  ReadAddressB <= 3'bzzz;
	  Fun          <= 4'bzzzz;
       end
       S1R21: begin
	  EstadoFuturo <= S1R22;
	  Control      <= 6'bzzz_zzz;
	  LoadSelect   <= 11'bzzzz_zzz_zz11;
	  WriteAddress <= Instruccion[8:6];
	  ReadAddressA <= 3'bzzz;
	  ReadAddressB <= 3'bzzz;
	  Fun          <= 4'bzzzz;
       end
       S1R22: begin
	  EstadoFuturo <= S1R23;
	  Control      <= 6'b100010;
	  LoadSelect   <= 11'bzz11_zzz_z1zz;
	  WriteAddress <= 3'bzzz;
	  ReadAddressA <= Instruccion[8:6];
	  ReadAddressB <= Instruccion[2:0];
	  Fun          <= 4'b0101;
       end
       S1R23: begin
	  EstadoFuturo <= SF1;
	  Control      <= 6'bzzz_zzz;
	  LoadSelect   <= 11'bzzzz_111_zz11;
	  WriteAddress <= Instruccion[8:6];
	  ReadAddressA <= 3'bzzz;
	  ReadAddressB <= 3'bzzz;
	  Fun          <= 4'bzzzz;
       end
       S1W20: begin
	  EstadoFuturo <= S1W21;
	  Control      <= 6'bzzz_zzz;
	  LoadSelect   <= 11'b11zz_zzz_zz11;
	  WriteAddress <= Instruccion[5:3];
	  ReadAddressA <= Instruccion[5:3];
	  ReadAddressB <= 3'bzzz;
	  Fun          <= 4'b1000;
       end
       S1W21: begin
	  EstadoFuturo <= S1W22;
	  Control      <= 6'b001011;
	  LoadSelect   <= 11'bzz11_zzz_z1zz;
	  WriteAddress <= 3'bzzz;
	  ReadAddressA <= Instruccion[5:3];
	  ReadAddressB <= Instruccion[2:0];
	  Fun          <= 4'b0101;
       end
       S1W22: begin
	  EstadoFuturo <= SF1;
	  Control      <= 6'b001010;
	  LoadSelect   <= 11'bzzzz_111_z111;
	  WriteAddress <= Instruccion[5:3];
	  ReadAddressA <= 3'bzzz;
	  ReadAddressB <= 3'bzzz;
	  Fun          <= 4'bzzzz;
       end
       S1R31: begin
	  EstadoFuturo <= S1R32;
	  Control      <= 6'b100010;
	  LoadSelect   <= 11'bzz01_zzz_z1zz;
	  WriteAddress <= 3'bzzz;
	  ReadAddressA <= 3'bzzz;
	  ReadAddressB <= 3'bzzz;
	  Fun          <= 4'bzzzz;
       end
       S1R32: begin
	  EstadoFuturo <= S1R33;
	  Control      <= 6'bzzz_zzz;
	  LoadSelect   <= 11'bzz01_zzz_zzzz;
	  WriteAddress <= 3'bzzz;
	  ReadAddressA <= 3'bzzz;
	  ReadAddressB <= 3'bzzz;
	  Fun          <= 4'bzzzz;
       end
       S1R33: begin
	  EstadoFuturo <= SF1;
	  Control      <= 6'bzzz_zzz;
	  LoadSelect   <= 11'bzzzz_11_zz11;
	  WriteAddress <= Instruccion[8:6];
	  ReadAddressA <= 3'bzzz;
	  ReadAddressB <= 3'bzzz;
	  Fun          <= 4'bzzzz;
       end
       S1W30: begin
	  EstadoFuturo <= S1W31;
	  Control      <= 6'b100010;
	  LoadSelect   <= 11'bzz01_zzz_z1zz;
	  WriteAddress <= 3'bzzz;
	  ReadAddressA <= 3'bzzz;
	  ReadAddressB <= 3'bzzz;
	  Fun          <= 4'bzzzz;
       end
       S1W31: begin
	  EstadoFuturo <= S1W32;
	  Control      <= 6'b001011;
	  LoadSelect   <= 11'b1101_zzz_z1zz;
	  WriteAddress <= 3'bzzz;
	  ReadAddressA <= Instruccion[5:3];
	  ReadAddressB <= 3'bzzz;
	  Fun          <= 4'b1000;
       end
       S1W32: begin
	  EstadoFuturo <= SF1;
	  Control      <= 6'b001010;
	  LoadSelect   <= 11'bzzzz_111_z1zzz;
	  WriteAddress <= 3'bzzz;
	  ReadAddressA <= 3'bzzz;
	  ReadAddressB <= 3'bzzz;
	  Fun          <= 4'bzzzz;
       end
       S21: begin
	  EstadoFuturo <= SF1;
	  Control      <= 6'bzzz_zzz;
	  LoadSelect   <= 11'bzzzz_001_zzzz;
	  WriteAddress <= 3'bzzz;
	  ReadAddressA <= 3'bzzz;
	  ReadAddressB <= 3'bzzz;
	  Fun          <= 4'bzzzz;
       end
       S22: begin
	  EstadoFuturo <= SF1;
	  Control      <= 6'bzzz_zzz;
	  LoadSelect   <= 11'bzzzz_111_zzzz;
	  WriteAddress <= 3'bzzz;
	  ReadAddressA <= 3'bzzz;
	  ReadAddressB <= 3'bzzz;
	  Fun          <= 4'bzzzz;
       end
       S23: begin
	  EstadoFuturo <= S24;
	  Control      <= 6'b010011;
	  LoadSelect   <= 11'b0111_111_z1zz;
	  WriteAddress <= 3'bzzz;
	  ReadAddressA <= Instruccion[5:3];
	  ReadAddressB <= 3'bzzz;
	  Fun          <= 4'b1000;
       end
       S24: begin
	  EstadoFuturo <= S25;
	  Control      <= 6'b010010;
	  LoadSelect   <= 11'bzzzz_zzz_z101;
	  WriteAddress <= Instruccion[5:3];
	  ReadAddressA <= Instruccion[5:3];
	  ReadAddressB <= 3'bzzz;
	  Fun          <= 4'b0111;
       end
       S25: begin
	  EstadoFuturo <= S26;
	  Control      <= 6'b001000;
	  LoadSelect   <= 11'bzzzz_zzz_z1zz;
	  WriteAddress <= 3'bzzz;
	  ReadAddressA <= 3'bzzz;
	  ReadAddressB <= 3'bzzz;
	  Fun          <= 4'bzzzz;
       end
       S26: begin
	  EstadoFuturo <= SF1;
	  Control      <= 6'bzzz_zzz;
	  LoadSelect   <= 11'bzzzz_001_zzzz;
	  WriteAddress <= 3'bzzz;
	  ReadAddressA <= 3'bzzz;
	  ReadAddressB <= 3'bzzz;
	  Fun          <= 4'bzzzz;
       end
       S27: begin
	  EstadoFuturo <= S28;
	  Control      <= 6'b100010;
	  LoadSelect   <= 11'bzz11_zzz_z101;
	  WriteAddress <= Instruccion[5:3];
	  ReadAddressA <= Instruccion[5:3];
	  ReadAddressB <= 3'bzzz;
	  Fun          <= 4'b0100;
       end
       S28: begin
	  EstadoFuturo <= SF1;
	  Control      <= 6'bzzz_zzz;
	  LoadSelect   <= 11'bzzzz_001_zzzz;
	  WriteAddress <= 3'bzzz;
	  ReadAddressA <= 3'bzzz;
	  ReadAddressB <= 3'bzzz;
	  Fun          <= 4'bzzzz;
       end
     endcase // case (EstadoPresente)
   

   
endmodule // UnidadDeControl

trunk/ld2ud/code/ciscud/UnidadDeControl_Lab.v
module UnidadDeControl_Lab (/*AUTOARG*/
   // Outputs
   Instruccion, Reloj, Reiniciar
   ) ;
   output reg [15:0] Instruccion;
   output reg Reloj, Reiniciar;

   wire [5:0] Rta_Control;
   /* -----\/----- EXCLUDED -----\/-----
    
    wire 	    LoadS;
    wire [1:0] SelectS;
    wire 	    NegS;
    -----/\----- EXCLUDED -----/\----- */
   
   wire       Rta_SelectDR, Rta_LoadDR;
   wire       Rta_SelectAR, Rta_LoadAR;
   
   wire [1:0] Rta_SelectPC;
   wire       Rta_LoadPC;
   
   wire       Rta_LoadIR, Rta_LoadCR;
   
   wire       Rta_WriteSelect, Rta_WriteEnable;
   wire [2:0] Rta_WriteAddress, Rta_ReadAddressA, Rta_ReadAddressB;
   
   wire [3:0] Rta_Fun;

   reg   [2:0] Rd, Rf1, Rf2;
   
   
   UnidadDeControl UC (Rta_Control,
		       Rta_SelectDR, Rta_LoadDR,
		       Rta_SelectAR, Rta_LoadAR,
		       Rta_SelectPC,Rta_LoadPC,
		       Rta_LoadIR, Rta_LoadCR,
		       Rta_WriteSelect, Rta_WriteEnable,
		       Rta_WriteAddress,Rta_ReadAddressA,Rta_ReadAddressB,
		       Rta_Fun,
		       //Los estimulos de prueba:
		       Instruccion,Reloj,Reiniciar);

   initial begin
      Reloj = 1'b0;
      Reiniciar = 1'b1;
      Instruccion <= 16'h0;
      Rd <= 3'b000;
      Rf1 <= 3'b001;
      Rf2 <= 3'b010;
   end

   initial begin
      repeat (64) begin
	 #1 Reloj <=  ~Reloj;
      end
   end
   
   initial begin
      repeat (34) begin
	 #1 Reiniciar <= ~Reiniciar;
	 #11 Reiniciar <= ~Reiniciar;
      end
   end

   initial begin
      repeat (34) begin
	 #12 Rd <= Rd+3;
	 Rf1 <= Rf1+3;
	 Rf2 <= Rf2+3;
      end
   end
   
   initial begin
      #12 Instruccion <= {7'h3,Rd,Rf1,Rf2};
      #12 Instruccion <= {7'h5,Rd,Rf1,Rf2};
      #12 Instruccion <= {7'h7,Rd,Rf1,Rf2};
   end

 
   initial begin
      $dumpfile("UnidadDeControl_Lab.vcd");
      $dumpvars;
   end
   
endmodule // UnidadDeControl_Lab

trunk/ld2ud/code/ciscud/UnidadDeControl_Lab.vcd
$date
	Tue Dec  8 20:21:25 2009
$end
$version
	Icarus Verilog
$end
$timescale
	1s
$end
$scope module UnidadDeControl_Lab $end
$var wire 6 ! Rta_Control[5:0] $end
$var wire 4 " Rta_Fun[3:0] $end
$var wire 1 # Rta_LoadAR $end
$var wire 1 $ Rta_LoadCR $end
$var wire 1 % Rta_LoadDR $end
$var wire 1 & Rta_LoadIR $end
$var wire 1 ' Rta_LoadPC $end
$var wire 3 ( Rta_ReadAddressA[2:0] $end
$var wire 3 ) Rta_ReadAddressB[2:0] $end
$var wire 1 * Rta_SelectAR $end
$var wire 1 + Rta_SelectDR $end
$var wire 2 , Rta_SelectPC[1:0] $end
$var wire 3 - Rta_WriteAddress[2:0] $end
$var wire 1 . Rta_WriteEnable $end
$var wire 1 / Rta_WriteSelect $end
$var reg 16 0 Instruccion[15:0] $end
$var reg 3 1 Rd[2:0] $end
$var reg 1 2 Reiniciar $end
$var reg 1 3 Reloj $end
$var reg 3 4 Rf1[2:0] $end
$var reg 3 5 Rf2[2:0] $end
$scope module UC $end
$var wire 16 6 Instruccion[15:0] $end
$var wire 1 2 Reiniciar $end
$var wire 1 3 Reloj $end
$var reg 6 7 Control[5:0] $end
$var reg 7 8 EstadoFuturo[6:0] $end
$var reg 7 9 EstadoPresente[6:0] $end
$var reg 4 : Fun[3:0] $end
$var reg 1 # LoadAR $end
$var reg 1 $ LoadCR $end
$var reg 1 % LoadDR $end
$var reg 1 & LoadIR $end
$var reg 1 ' LoadPC $end
$var reg 11 ; LoadSelect[10:0] $end
$var reg 3 < ReadAddressA[2:0] $end
$var reg 3 = ReadAddressB[2:0] $end
$var reg 1 * SelectAR $end
$var reg 1 + SelectDR $end
$var reg 2 > SelectPC[1:0] $end
$var reg 3 ? WriteAddress[2:0] $end
$var reg 1 . WriteEnable $end
$var reg 1 / WriteSelect $end
$upscope $end
$upscope $end
$enddefinitions $end
#0
$dumpvars
bx ?
bx >
bx =
bx <
bx ;
bx :
bx 9
b0 8
bx 7
b0 6
b10 5
b1 4
03
12
b0 1
b0 0
x/
x.
bx -
bx ,
x+
x*
bx )
bx (
x'
x&
x%
x$
x#
bx "
bx !
$end
#1
bz "
bz :
bz )
bz =
bz (
bz <
bz -
bz ?
bz1zz ;
b100100 !
b100100 7
b1 8
b0 9
02
13
#2
03
#3
bz1111zzz ;
bz !
bz 7
b10 8
b1 9
13
#4
03
#5
b11 8
b10 9
13
#6
03
#7
b0 "
b0 :
b0 )
b0 =
b0 (
b0 <
b0 -
b0 ?
bz01 ;
b0 8
b11 9
13
#8
03
#9
bz "
bz :
bz )
bz =
bz (
bz <
bz -
bz ?
bz1zz ;
b100100 !
b100100 7
b1 8
b0 9
13
#10
03
#11
bz1111zzz ;
bz !
bz 7
b10 8
b1 9
13
#12
b0 8
03
12
b11000001010 0
b11000001010 6
b101 5
b100 4
b11 1
#13
bz1zz ;
b100100 !
b100100 7
b1 8
b0 9
13
02
#14
03
#15
bz1111zzz ;
bz !
bz 7
b10 8
b1 9
13
#16
03
#17
b11 8
b10 9
13
#18
03
#19
b11 "
b11 :
b10 )
b10 =
b1 (
b1 <
b0 -
b0 ?
bz01 ;
b0 8
b11 9
13
#20
03
#21
bz "
bz :
bz )
bz =
bz (
bz <
bz -
bz ?
bz1zz ;
b100100 !
b100100 7
b1 8
b0 9
13
#22
03
#23
bz1111zzz ;
bz !
bz 7
b10 8
b1 9
13
#24
b0 8
03
12
b101011100101 0
b101011100101 6
b0 5
b111 4
b110 1
#25
bz1zz ;
b100100 !
b100100 7
b1 8
b0 9
13
02
#26
03
#27
bz1111zzz ;
bz !
bz 7
b10 8
b1 9
13
#28
03
#29
b100 8
b10 9
13
#30
03
#31
b101 "
b101 :
b101 )
b101 =
b100 (
b100 <
b11 -
b11 ?
bz01 ;
b0 8
b100 9
13
#32
03
#33
bz "
bz :
bz )
bz =
bz (
bz <
bz -
bz ?
bz1zz ;
b100100 !
b100100 7
b1 8
b0 9
13
#34
03
#35
bz1111zzz ;
bz !
bz 7
b10 8
b1 9
13
#36
b0 8
03
12
b111110111000 0
b111110111000 6
b11 5
b10 4
b1 1
#37
bz1zz ;
b100100 !
b100100 7
b1 8
b0 9
13
02
#38
03
#39
bz1111zzz ;
bz !
bz 7
b10 8
b1 9
13
#40
03
#41
b100 8
b10 9
13
#42
03
#43
b111 "
b111 :
b0 )
b0 =
b111 (
b111 <
b110 -
b110 ?
bz01 ;
b0 8
b100 9
13
#44
03
#45
bz "
bz :
bz )
bz =
bz (
bz <
bz -
bz ?
bz1zz ;
b100100 !
b100100 7
b1 8
b0 9
13
#46
03
#47
bz1111zzz ;
bz !
bz 7
b10 8
b1 9
13
#48
b0 8
03
12
b110 5
b101 4
b100 1
#49
bz1zz ;
b100100 !
b100100 7
b1 8
b0 9
13
02
#50
03
#51
bz1111zzz ;
bz !
bz 7
b10 8
b1 9
13
#52
03
#53
b100 8
b10 9
13
#54
03
#55
b111 "
b111 :
b0 )
b0 =
b111 (
b111 <
b110 -
b110 ?
bz01 ;
b0 8
b100 9
13
#56
03
#57
bz "
bz :
bz )
bz =
bz (
bz <
bz -
bz ?
bz1zz ;
b100100 !
b100100 7
b1 8
b0 9
13
#58
03
#59
bz1111zzz ;
bz !
bz 7
b10 8
b1 9
13
#60
b0 8
03
12
b1 5
b0 4
b111 1
#61
bz1zz ;
b100100 !
b100100 7
b1 8
b0 9
13
02
#62
03
#63
bz1111zzz ;
bz !
bz 7
b10 8
b1 9
13
#64
03
#72
b0 8
12
b100 5
b11 4
b10 1
#73
02
#84
12
b111 5
b110 4
b101 1
#85
02
#96
12
b10 5
b1 4
b0 1
#97
02
#108
12
b101 5
b100 4
b11 1
#109
02
#120
12
b0 5
b111 4
b110 1
#121
02
#132
12
b11 5
b10 4
b1 1
#133
02
#144
12
b110 5
b101 4
b100 1
#145
02
#156
12
b1 5
b0 4
b111 1
#157
02
#168
12
b100 5
b11 4
b10 1
#169
02
#180
12
b111 5
b110 4
b101 1
#181
02
#192
12
b10 5
b1 4
b0 1
#193
02
#204
12
b101 5
b100 4
b11 1
#205
02
#216
12
b0 5
b111 4
b110 1
#217
02
#228
12
b11 5
b10 4
b1 1
#229
02
#240
12
b110 5
b101 4
b100 1
#241
02
#252
12
b1 5
b0 4
b111 1
#253
02
#264
12
b100 5
b11 4
b10 1
#265
02
#276
12
b111 5
b110 4
b101 1
#277
02
#288
12
b10 5
b1 4
b0 1
#289
02
#300
12
b101 5
b100 4
b11 1
#301
02
#312
12
b0 5
b111 4
b110 1
#313
02
#324
12
b11 5
b10 4
b1 1
#325
02
#336
12
b110 5
b101 4
b100 1
#337
02
#348
12
b1 5
b0 4
b111 1
#349
02
#360
12
b100 5
b11 4
b10 1
#361
02
#372
12
b111 5
b110 4
b101 1
#373
02
#384
12
b10 5
b1 4
b0 1
#385
02
#396
12
b101 5
b100 4
b11 1
#397
02
#408
12
b0 5
b111 4
b110 1
