trunk/ld2ud/code/Decodificador3a8.v
module Decodificador3a8 (/*AUTOARG*/
   // Outputs
   Salida,
   // Inputs
   Entrada
   ) ;
   output [7:0] Salida;
   input  [2:0] Entrada;

   and (Salida[0],Entrada[2],Entrada[1],Entrada[0]);
   and (Salida[1],Entrada[2],Entrada[1],~Entrada[0]);
   and (Salida[2],Entrada[2],~Entrada[1],Entrada[0]);
   and (Salida[3],Entrada[2],~Entrada[1],~Entrada[0]);
   and (Salida[4],~Entrada[2],Entrada[1],Entrada[0]);
   and (Salida[5],~Entrada[2],Entrada[1],~Entrada[0]);
   and (Salida[6],~Entrada[2],~Entrada[1],Entrada[0]);
   and (Salida[7],~Entrada[2],~Entrada[1],~Entrada[0]);   
   
endmodule // Decodificador3a8

ld2ud/code/Comparador22Numeros6Bit_Compuertas.v
module Comparador22Numeros6Bit_Compuertas (/*AUTOARG*/
   // Para más info revisar APÉNDICE al final del archivo
   // Outputs
   Salida,
   // Inputs
   Entrada
   ) ;
   output Salida; //Es uno(1) si Entrada pertenece a conjunto Combinación
   input  [5:0] Entrada; //Número que se desea saber si pertenece a conjunto Combinación

   wire   [21:0] Nodo; //Nodo[x] es salida de cada decodificador básico
   
   and Dec01 (Nodo[21],~Entrada[5],~Entrada[4],~Entrada[3],~Entrada[2],~Entrada[1],Entrada[0]);
   and Dec02 (Nodo[20],~Entrada[5],~Entrada[4],~Entrada[3],~Entrada[2],Entrada[1],~Entrada[0]);
   and Dec03 (Nodo[19],~Entrada[5],~Entrada[4],~Entrada[3],~Entrada[2],Entrada[1],Entrada[0]);
   and Dec04 (Nodo[18],~Entrada[5],~Entrada[4],~Entrada[3],Entrada[2],~Entrada[1],Entrada[0]);
   and Dec05 (Nodo[17],~Entrada[5],~Entrada[4],Entrada[3],~Entrada[2],Entrada[1],~Entrada[0]);
   and Dec06 (Nodo[16],~Entrada[5],~Entrada[4],Entrada[3],Entrada[2],~Entrada[1],~Entrada[0]);
   and Dec07 (Nodo[15],~Entrada[5],~Entrada[4],Entrada[3],Entrada[2],~Entrada[1],Entrada[0]);
   and Dec08 (Nodo[14],~Entrada[5],~Entrada[4],Entrada[3],Entrada[2],Entrada[1],Entrada[0]);
   and Dec09 (Nodo[13],~Entrada[5],Entrada[4],~Entrada[3],Entrada[2],~Entrada[1],~Entrada[0]);
   and Dec10 (Nodo[12],~Entrada[5],Entrada[4],~Entrada[3],Entrada[2],~Entrada[1],Entrada[0]);
   and Dec11 (Nodo[11],~Entrada[5],Entrada[4],~Entrada[3],Entrada[2],Entrada[1],~Entrada[0]);
   and Dec12 (Nodo[10],~Entrada[5],Entrada[4],~Entrada[3],Entrada[2],Entrada[1],Entrada[0]);
   and Dec13 (Nodo[9],~Entrada[5],Entrada[4],Entrada[3],~Entrada[2],~Entrada[1],Entrada[0]);
   and Dec14 (Nodo[8],~Entrada[5],Entrada[4],Entrada[3],Entrada[2],Entrada[1],~Entrada[0]);
   and Dec15 (Nodo[7],~Entrada[5],Entrada[4],Entrada[3],Entrada[2],Entrada[1],Entrada[0]);
   and Dec16 (Nodo[6],Entrada[5],~Entrada[4],~Entrada[3],~Entrada[2],~Entrada[1],~Entrada[0]);
   and Dec17 (Nodo[5],Entrada[5],~Entrada[4],~Entrada[3],~Entrada[2],~Entrada[1],Entrada[0]);
   and Dec18 (Nodo[4],Entrada[5],~Entrada[4],~Entrada[3],~Entrada[2],Entrada[1],Entrada[0]);
   and Dec19 (Nodo[3],Entrada[5],Entrada[4],~Entrada[3],~Entrada[2],Entrada[1],~Entrada[0]);
   and Dec20 (Nodo[2],Entrada[5],Entrada[4],~Entrada[3],~Entrada[2],Entrada[1],Entrada[0]);
   and Dec21 (Nodo[1],Entrada[5],Entrada[4],~Entrada[3],Entrada[2],~Entrada[1],~Entrada[0]);
   and Dec22 (Nodo[0],Entrada[5],Entrada[4],~Entrada[3],Entrada[2],~Entrada[1],Entrada[0]);

   or (Salida,Nodo[0],Nodo[1],Nodo[2],Nodo[3],Nodo[4],Nodo[5],Nodo[6],Nodo[7],Nodo[8],Nodo[9],Nodo[10],Nodo[11],Nodo[12],Nodo[13],Nodo[14],Nodo[15],Nodo[16],Nodo[17],Nodo[18],Nodo[19],Nodo[20],Nodo[21]);
   
   
endmodule // Comparador22Numeros6Bit_Compuertas


/* APÉNDICE
 * Tenemos el conjunto Combinación que contiene 22 números diferentes de 6 bit
 * y deseamos que cuando Entrada pertenezca al conjunto Combinación Salida sea uno(1)
 *
 * Combinación  Binario  Salida
 * 01      	000_001       1
 * 02      	000_010       1
 * 03      	000_011       1
 * 05      	000_101       1
 * 10      	001_010       1
 * 12      	001_100       1
 * 13      	001_101       1
 * 15      	001_111       1
 * 20      	010_100       1
 * 21      	010_101       1
 * 22      	010_110       1
 * 23      	010_111       1
 * 25      	011_001       1
 * 30      	011_110       1
 * 31      	011_111       1
 * 32      	100_000       1
 * 33      	100_001       1
 * 35      	100_011       1
 * 50      	110_010       1
 * 51      	110_011       1
 * 52      	110_100       1
 * 53      	110_101       1
 *
 * Este módulo implementa un decodificador binario básico (Referencia:Fundamentos de 
 * Sistemas Digitales,edición 7,pág 350,Thomas L. Floyd) llamado DecXX para cada elemento
 * del conjunto Combinación y la salida de los 22 DecXX (Nodo[x]) entra en una compuerta or.
 */

trunk/ld2ud/code/Laboratorio2_Lab.v
module Laboratorio2_Lab (/*AUTOARG*/ ) ;
   wire   RtaComparador22Numeros6Bit_Compuertas;
   wire   [7:0] RtaDecodificador;
   
   reg [5:0]   Estimulo;
   reg   [2:0] EstimuloDecodificador;
   
   Comparador22Numeros6Bit_Compuertas U2 (RtaComparador22Numeros6Bit_Compuertas,Estimulo[5:0]);

   Decodificador3a8 U3 (RtaDecodificador,EstimuloDecodificador);
   
   
   initial begin
      Estimulo = 6'b000000;
      EstimuloDecodificador = 3'b000;
   end

   initial begin
      repeat (62) begin
	 #1 Estimulo <= Estimulo + 1;
      end
   end

   initial begin
      repeat (8) begin
	 #1 EstimuloDecodificador = EstimuloDecodificador + 1;
      end
   end
   

   initial begin
      $dumpfile ("Laboratorio2_Lab.vcd");
      $dumpvars;
   end
   
endmodule // Laboratorio2_Lab

ld2ud/code/Laboratorio2_Lab.vcd
$date
	Sat Oct  3 19:56:43 2009
$end
$version
	Icarus Verilog
$end
$timescale
	1s
$end
$scope module Laboratorio2_Lab $end
$var wire 1 ! RtaComparador22Numeros6Bit_Compuertas $end
$var wire 8 " RtaDecodificador[7:0] $end
$var reg 6 # Estimulo[5:0] $end
$var reg 3 $ EstimuloDecodificador[2:0] $end
$scope module U2 $end
$var wire 6 % Entrada[5:0] $end
$var wire 22 & Nodo[21:0] $end
$var wire 1 ! Salida $end
$upscope $end
$scope module U3 $end
$var wire 3 ' Entrada[2:0] $end
$var wire 8 ( Salida[7:0] $end
$upscope $end
$upscope $end
$enddefinitions $end
#0
$dumpvars
b10000000 (
b0 '
b0 &
b0 %
b0 $
b0 #
b10000000 "
0!
$end
#1
1!
b1000000000000000000000 &
b1 #
b1 %
b1000000 "
b1000000 (
b1 $
b1 '
#2
b100000000000000000000 &
b10 #
b10 %
b100000 "
b100000 (
b10 $
b10 '
#3
b10000000000000000000 &
b11 #
b11 %
b10000 "
b10000 (
b11 $
b11 '
#4
0!
b0 &
b100 #
b100 %
b1000 "
b1000 (
b100 $
b100 '
#5
1!
b1000000000000000000 &
b101 #
b101 %
b100 "
b100 (
b101 $
b101 '
#6
0!
b0 &
b110 #
b110 %
b10 "
b10 (
b110 $
b110 '
#7
b111 #
b111 %
b1 "
b1 (
b111 $
b111 '
#8
b1000 #
b1000 %
b10000000 "
b10000000 (
b0 $
b0 '
#9
b1001 #
b1001 %
#10
1!
b100000000000000000 &
b1010 #
b1010 %
#11
0!
b0 &
b1011 #
b1011 %
#12
1!
b10000000000000000 &
b1100 #
b1100 %
#13
b1000000000000000 &
b1101 #
b1101 %
#14
0!
b0 &
b1110 #
b1110 %
#15
1!
b100000000000000 &
b1111 #
b1111 %
#16
0!
b0 &
b10000 #
b10000 %
#17
b10001 #
b10001 %
#18
b10010 #
b10010 %
#19
b10011 #
b10011 %
#20
1!
b10000000000000 &
b10100 #
b10100 %
#21
b1000000000000 &
b10101 #
b10101 %
#22
b100000000000 &
b10110 #
b10110 %
#23
b10000000000 &
b10111 #
b10111 %
#24
0!
b0 &
b11000 #
b11000 %
#25
1!
b1000000000 &
b11001 #
b11001 %
#26
0!
b0 &
b11010 #
b11010 %
#27
b11011 #
b11011 %
#28
b11100 #
b11100 %
#29
b11101 #
b11101 %
#30
1!
b100000000 &
b11110 #
b11110 %
#31
b10000000 &
b11111 #
b11111 %
#32
1!
b1000000 &
b100000 #
b100000 %
#33
b100000 &
b100001 #
b100001 %
#34
0!
b0 &
b100010 #
b100010 %
#35
1!
b10000 &
b100011 #
b100011 %
#36
0!
b0 &
b100100 #
b100100 %
#37
b100101 #
b100101 %
#38
b100110 #
b100110 %
#39
b100111 #
b100111 %
#40
b101000 #
b101000 %
#41
b101001 #
b101001 %
#42
b101010 #
b101010 %
#43
b101011 #
b101011 %
#44
b101100 #
b101100 %
#45
b101101 #
b101101 %
#46
b101110 #
b101110 %
#47
b101111 #
b101111 %
#48
b110000 #
b110000 %
#49
b110001 #
b110001 %
#50
1!
b1000 &
b110010 #
b110010 %
#51
b100 &
b110011 #
b110011 %
#52
1!
b10 &
b110100 #
b110100 %
#53
b1 &
b110101 #
b110101 %
#54
0!
b0 &
b110110 #
b110110 %
#55
b110111 #
b110111 %
#56
b111000 #
b111000 %
#57
b111001 #
b111001 %
#58
b111010 #
b111010 %
#59
b111011 #
b111011 %
#60
b111100 #
b111100 %
#61
b111101 #
b111101 %
#62
b111110 #
b111110 %
