ld2ud/code/Decodificador2a4.v
module Decodificador2a4 (/*AUTOARG*/
   // Outputs
   Salida,
   // Inputs
   Entrada, Enable
   ) ;
   output [3:0] Salida;
   input  [1:0] Entrada;
   input  Enable;

   wire   NodoA, NodoB;

   assign NodoA = ~ Entrada[0];
   assign NodoB = ~ Entrada[1];
   assign Salida[0] = NodoA & NodoB & Enable;
   assign Salida[1] = Entrada[0] & NodoB & Enable; 
   assign Salida[2] = Entrada[1] & NodoA & Enable;
   assign Salida[3] = Entrada[0] & Entrada[1] & Enable;
   
endmodule // Decodificador2a4


//referencia: http://en.wikipedia.org/wiki/File:Decoder_Example.svg
//tags: teoria

// para poder hacer el decoder 4a16 usando decoders 2a4 requería enable:
//http://www.ee.olemiss.edu/matt/EE385/385_L2/sld006.htm

ld2ud/code/Decodificador4a16.v

module Decodificador4a16 (/*AUTOARG*/
   // Outputs
   Salida,
   // Inputs
   Entrada, Enable
   ) ;
   output [15:0] Salida;
   input  [3:0] Entrada;
   input  Enable;

   wire   NodoA, NodoB, NodoC, NodoD;
   
   Decodificador2a4 U1 ({NodoA,NodoB,NodoC,NodoD},Entrada[3:2],Enable);
   Decodificador2a4 U2 (Salida[15:12],Entrada[1:0],NodoA);
   Decodificador2a4 U3 (Salida[11:8],Entrada[1:0],NodoB);
   Decodificador2a4 U4 (Salida[7:4],Entrada[1:0],NodoC);
   Decodificador2a4 U5 (Salida[3:0],Entrada[1:0],NodoD);
endmodule // Decodificador4a16


// Referencia: http://ecpe.ee.iastate.edu/arun/CprE281_F05/lab/labw06a/labw06a_files/image009.jpg

//tags: teoria

trunk/ld2ud/code/Leccion3_Lab.v
module Leccion3_Lab (/*AUTOARG*/) ;
   wire   [3:0] RtaDecodificador2a4;
   wire   [15:0] RtaDecodificador4a16;
   reg   [2:0] EstimuloDecodificador2a4;
   reg   [4:0] EstimuloDecodificador4a16;
   
   Decodificador2a4 U1 (RtaDecodificador2a4,EstimuloDecodificador2a4[1:0], EstimuloDecodificador2a4[2]);

   Decodificador4a16 U2 (RtaDecodificador4a16,EstimuloDecodificador4a16[3:0],EstimuloDecodificador4a16[4]);
   
   initial begin
      EstimuloDecodificador2a4 = 'b000;
      EstimuloDecodificador4a16 = 'b00000;
   end

   initial begin
      repeat (8) begin
	 #1 EstimuloDecodificador2a4 <= EstimuloDecodificador2a4 + 1;
      end
      repeat (32) begin
	 #1 EstimuloDecodificador4a16 <= EstimuloDecodificador4a16 + 1;
      end
      
   end

   initial begin
      $dumpfile("Leccion3_Lab.vcd");
      $dumpvars;
   end
   
endmodule // Leccion3_Lab

//tags: teoria

ld2ud/code/Leccion3_Lab.vcd
$date
	Sun Sep 20 22:04:21 2009
$end
$version
	Icarus Verilog
$end
$timescale
	1s
$end
$scope module Leccion3_Lab $end
$var wire 4 ! RtaDecodificador2a4[3:0] $end
$var wire 16 " RtaDecodificador4a16[15:0] $end
$var reg 3 # EstimuloDecodificador2a4[2:0] $end
$var reg 5 $ EstimuloDecodificador4a16[4:0] $end
$scope module U1 $end
$var wire 1 % Enable $end
$var wire 2 & Entrada[1:0] $end
$var wire 1 ' NodoA $end
$var wire 1 ( NodoB $end
$var wire 4 ) Salida[3:0] $end
$upscope $end
$scope module U2 $end
$var wire 1 * Enable $end
$var wire 4 + Entrada[3:0] $end
$var wire 1 , NodoA $end
$var wire 1 - NodoB $end
$var wire 1 . NodoC $end
$var wire 1 / NodoD $end
$var wire 16 0 Salida[15:0] $end
$scope module U1 $end
$var wire 1 * Enable $end
$var wire 2 1 Entrada[1:0] $end
$var wire 1 2 NodoA $end
$var wire 1 3 NodoB $end
$var wire 4 4 Salida[3:0] $end
$upscope $end
$scope module U2 $end
$var wire 1 , Enable $end
$var wire 2 5 Entrada[1:0] $end
$var wire 1 6 NodoA $end
$var wire 1 7 NodoB $end
$var wire 4 8 Salida[3:0] $end
$upscope $end
$scope module U3 $end
$var wire 1 - Enable $end
$var wire 2 9 Entrada[1:0] $end
$var wire 1 : NodoA $end
$var wire 1 ; NodoB $end
$var wire 4 < Salida[3:0] $end
$upscope $end
$scope module U4 $end
$var wire 1 . Enable $end
$var wire 2 = Entrada[1:0] $end
$var wire 1 > NodoA $end
$var wire 1 ? NodoB $end
$var wire 4 @ Salida[3:0] $end
$upscope $end
$scope module U5 $end
$var wire 1 / Enable $end
$var wire 2 A Entrada[1:0] $end
$var wire 1 B NodoA $end
$var wire 1 C NodoB $end
$var wire 4 D Salida[3:0] $end
$upscope $end
$upscope $end
$upscope $end
$enddefinitions $end
#0
$dumpvars
b0 D
1C
1B
b0 A
b0 @
1?
1>
b0 =
b0 <
1;
1:
b0 9
b0 8
17
16
b0 5
b0 4
13
12
b0 1
b0 0
0/
0.
0-
0,
b0 +
0*
b0 )
1(
1'
b0 &
0%
b0 $
b0 #
b0 "
b0 !
$end
#1
0'
b1 #
b1 &
#2
0(
1'
b10 #
b10 &
#3
0'
b11 #
b11 &
#4
b1 !
b1 )
1(
1'
1%
b100 #
b0 &
#5
b10 !
b10 )
0'
b101 #
b1 &
#6
b100 !
b100 )
0(
1'
b110 #
b10 &
#7
b1000 !
b1000 )
0'
b111 #
b11 &
#8
b0 !
b0 )
1(
1'
0%
b0 #
b0 &
#9
06
0:
0>
0B
b1 $
b1 +
b1 5
b1 9
b1 =
b1 A
#10
07
0;
0?
0C
16
1:
1>
1B
b10 $
b10 +
b10 5
b10 9
b10 =
b10 A
#11
06
0:
0>
0B
b11 $
b11 +
b11 5
b11 9
b11 =
b11 A
#12
02
17
1;
1?
1C
16
1:
1>
1B
b1 1
b100 $
b100 +
b0 5
b0 9
b0 =
b0 A
#13
06
0:
0>
0B
b101 $
b101 +
b1 5
b1 9
b1 =
b1 A
#14
07
0;
0?
0C
16
1:
1>
1B
b110 $
b110 +
b10 5
b10 9
b10 =
b10 A
#15
06
0:
0>
0B
b111 $
b111 +
b11 5
b11 9
b11 =
b11 A
#16
03
12
17
1;
1?
1C
16
1:
1>
1B
b10 1
b1000 $
b1000 +
b0 5
b0 9
b0 =
b0 A
#17
06
0:
0>
0B
b1001 $
b1001 +
b1 5
b1 9
b1 =
b1 A
#18
07
0;
0?
0C
16
1:
1>
1B
b1010 $
b1010 +
b10 5
b10 9
b10 =
b10 A
#19
06
0:
0>
0B
b1011 $
b1011 +
b11 5
b11 9
b11 =
b11 A
#20
02
17
1;
1?
1C
16
1:
1>
1B
b11 1
b1100 $
b1100 +
b0 5
b0 9
b0 =
b0 A
#21
06
0:
0>
0B
b1101 $
b1101 +
b1 5
b1 9
b1 =
b1 A
#22
07
0;
0?
0C
16
1:
1>
1B
b1110 $
b1110 +
b10 5
b10 9
b10 =
b10 A
#23
06
0:
0>
0B
b1111 $
b1111 +
b11 5
b11 9
b11 =
b11 A
#24
b1 "
b1 0
b1 D
1/
0,
b1 4
13
12
17
1;
1?
1C
16
1:
1>
1B
1*
b0 1
b10000 $
b0 +
b0 5
b0 9
b0 =
b0 A
#25
b10 "
b10 0
b10 D
06
0:
0>
0B
b10001 $
b1 +
b1 5
b1 9
b1 =
b1 A
#26
b100 "
b100 0
b100 D
07
0;
0?
0C
16
1:
1>
1B
b10010 $
b10 +
b10 5
b10 9
b10 =
b10 A
#27
b1000 "
b1000 0
b1000 D
06
0:
0>
0B
b10011 $
b11 +
b11 5
b11 9
b11 =
b11 A
#28
0/
b1 @
1.
b10 4
b10000 "
b10000 0
b0 D
02
17
1;
1?
1C
16
1:
1>
1B
b1 1
b10100 $
b100 +
b0 5
b0 9
b0 =
b0 A
#29
b100000 "
b100000 0
b10 @
06
0:
0>
0B
b10101 $
b101 +
b1 5
b1 9
b1 =
b1 A
#30
b1000000 "
b1000000 0
b100 @
07
0;
0?
0C
16
1:
1>
1B
b10110 $
b110 +
b10 5
b10 9
b10 =
b10 A
#31
b10000000 "
b10000000 0
b1000 @
06
0:
0>
0B
b10111 $
b111 +
b11 5
b11 9
b11 =
b11 A
#32
b1 <
1-
0.
b100 4
b100000000 "
b100000000 0
b0 @
03
12
17
1;
1?
1C
16
1:
1>
1B
b10 1
b11000 $
b1000 +
b0 5
b0 9
b0 =
b0 A
#33
b1000000000 "
b1000000000 0
b10 <
06
0:
0>
0B
b11001 $
b1001 +
b1 5
b1 9
b1 =
b1 A
#34
b10000000000 "
b10000000000 0
b100 <
07
0;
0?
0C
16
1:
1>
1B
b11010 $
b1010 +
b10 5
b10 9
b10 =
b10 A
#35
b100000000000 "
b100000000000 0
b1000 <
06
0:
0>
0B
b11011 $
b1011 +
b11 5
b11 9
b11 =
b11 A
#36
0-
b1 8
1,
b1000 4
b1000000000000 "
b1000000000000 0
b0 <
02
17
1;
1?
1C
16
1:
1>
1B
b11 1
b11100 $
b1100 +
b0 5
b0 9
b0 =
b0 A
#37
b10000000000000 "
b10000000000000 0
b10 8
06
0:
0>
0B
b11101 $
b1101 +
b1 5
b1 9
b1 =
b1 A
#38
b100000000000000 "
b100000000000000 0
b100 8
07
0;
0?
0C
16
1:
1>
1B
b11110 $
b1110 +
b10 5
b10 9
b10 =
b10 A
#39
b1000000000000000 "
b1000000000000000 0
b1000 8
06
0:
0>
0B
b11111 $
b1111 +
b11 5
b11 9
b11 =
b11 A
#40
b0 "
b0 0
b0 8
0,
b0 4
13
12
17
1;
1?
1C
16
1:
1>
1B
0*
b0 1
b0 $
b0 +
b0 5
b0 9
b0 =
b0 A
